[
  {
    "pages_id": "430",
    "seq_id": "1",
    "name": "Large Intestine",
    "id": "22607"
  },
  {
    "pages_id": "430",
    "seq_id": "2",
    "name": "Large Intestine",
    "id": "22608"
  },
  {
    "pages_id": "430",
    "seq_id": "3",
    "name": "Large Intestine",
    "id": "22609"
  },
  {
    "pages_id": "430",
    "seq_id": "4",
    "name": "Liver",
    "id": "22610"
  },
  {
    "pages_id": "430",
    "seq_id": "5",
    "name": "Small Intestine",
    "id": "22611"
  },
  {
    "pages_id": "430",
    "seq_id": "6",
    "name": "Small Intestine",
    "id": "22612"
  },
  {
    "pages_id": "430",
    "seq_id": "7",
    "name": "Small Intestine",
    "id": "22613"
  },
  {
    "pages_id": "430",
    "seq_id": "8",
    "name": "Spleen",
    "id": "22614"
  },
  {
    "pages_id": "430",
    "seq_id": "9",
    "name": "Spleen",
    "id": "22615"
  },
  {
    "pages_id": "430",
    "seq_id": "10",
    "name": "Spleen",
    "id": "22616"
  },
  {
    "pages_id": "430",
    "seq_id": "11",
    "name": "Spleen",
    "id": "22617"
  },
  {
    "pages_id": "430",
    "seq_id": "12",
    "name": "Spleen",
    "id": "22618"
  },
  {
    "pages_id": "430",
    "seq_id": "13",
    "name": "Spleen",
    "id": "22619"
  },
  {
    "pages_id": "430",
    "seq_id": "14",
    "name": "Stomach",
    "id": "22620"
  },
  {
    "pages_id": "430",
    "seq_id": "15",
    "name": "Lungs",
    "id": "22621"
  },
  {
    "pages_id": "430",
    "seq_id": "16",
    "name": "Lungs",
    "id": "22622"
  },
  {
    "pages_id": "430",
    "seq_id": "17",
    "name": "Heart",
    "id": "22623"
  },
  {
    "pages_id": "430",
    "seq_id": "18",
    "name": "Abdominal Aorta",
    "id": "22624"
  },
  {
    "pages_id": "430",
    "seq_id": "19",
    "name": "Common Bile Duct",
    "id": "22625"
  }
]