[
  {
    "id": "42867",
    "pages_id": "15929",
    "seq_id": "1",
    "name": "Anterior Longitudinal Ligament"
  },
  {
    "id": "42868",
    "pages_id": "15929",
    "seq_id": "2",
    "name": "Anterior Longitudinal Ligament"
  },
  {
    "id": "42869",
    "pages_id": "15929",
    "seq_id": "3",
    "name": "Acromioclavicular Ligament"
  },
  {
    "id": "42870",
    "pages_id": "15929",
    "seq_id": "4",
    "name": "Anterior Longitudinal Ligament"
  },
  {
    "id": "42871",
    "pages_id": "15929",
    "seq_id": "5",
    "name": "Anterior Longitudinal Ligament"
  },
  {
    "id": "42872",
    "pages_id": "15929",
    "seq_id": "6",
    "name": "C2 (Axis) - 2nd Cervical Vertebra"
  },
  {
    "id": "42873",
    "pages_id": "15929",
    "seq_id": "7",
    "name": "C1 (Atlas) - 1st Cervical Vertebra"
  },
  {
    "id": "42874",
    "pages_id": "15929",
    "seq_id": "8",
    "name": "C1 (Atlas) - 1st Cervical Vertebra"
  },
  {
    "id": "42875",
    "pages_id": "15929",
    "seq_id": "9",
    "name": "C3 (3rd Cervical Vertebra)"
  },
  {
    "id": "42876",
    "pages_id": "15929",
    "seq_id": "10",
    "name": "C3 (3rd Cervical Vertebra)"
  },
  {
    "id": "42877",
    "pages_id": "15929",
    "seq_id": "11",
    "name": "C3 (3rd Cervical Vertebra)"
  },
  {
    "id": "42878",
    "pages_id": "15929",
    "seq_id": "12",
    "name": "C4 (4th Cervical Vertebra)"
  },
  {
    "id": "42879",
    "pages_id": "15929",
    "seq_id": "13",
    "name": "C4 (4th Cervical Vertebra)"
  },
  {
    "id": "42880",
    "pages_id": "15929",
    "seq_id": "14",
    "name": "C6 (6th Cervical Vertebra)"
  },
  {
    "id": "42881",
    "pages_id": "15929",
    "seq_id": "15",
    "name": "C5 (5th Cervical Vertebra)"
  },
  {
    "id": "42882",
    "pages_id": "15929",
    "seq_id": "16",
    "name": "C5 (5th Cervical Vertebra)"
  },
  {
    "id": "42883",
    "pages_id": "15929",
    "seq_id": "17",
    "name": "C6 (6th Cervical Vertebra)"
  },
  {
    "id": "42884",
    "pages_id": "15929",
    "seq_id": "18",
    "name": "C6 (6th Cervical Vertebra)"
  },
  {
    "id": "42885",
    "pages_id": "15929",
    "seq_id": "19",
    "name": "C6 (6th Cervical Vertebra)"
  },
  {
    "id": "42886",
    "pages_id": "15929",
    "seq_id": "20",
    "name": "C7 (7th Cervical Vertebra)"
  },
  {
    "id": "42887",
    "pages_id": "15929",
    "seq_id": "21",
    "name": "C7 (7th Cervical Vertebra)"
  },
  {
    "id": "42888",
    "pages_id": "15929",
    "seq_id": "22",
    "name": "Capsular Ligament of the Shoulder"
  },
  {
    "id": "42889",
    "pages_id": "15929",
    "seq_id": "23",
    "name": "C7 (7th Cervical Vertebra)"
  },
  {
    "id": "42890",
    "pages_id": "15929",
    "seq_id": "24",
    "name": "Capsular Ligament of the Shoulder"
  },
  {
    "id": "42891",
    "pages_id": "15929",
    "seq_id": "25",
    "name": "T4 (4th Thoracic Vertebra)"
  },
  {
    "id": "42892",
    "pages_id": "15929",
    "seq_id": "26",
    "name": "Teeth"
  },
  {
    "id": "42893",
    "pages_id": "15929",
    "seq_id": "27",
    "name": "Superior Transverse Scapular Ligament"
  },
  {
    "id": "42894",
    "pages_id": "15929",
    "seq_id": "28",
    "name": "Scapula"
  },
  {
    "id": "42895",
    "pages_id": "15929",
    "seq_id": "29",
    "name": "Sphenoid Bone"
  },
  {
    "id": "42896",
    "pages_id": "15929",
    "seq_id": "30",
    "name": "Sphenoid Bone"
  },
  {
    "id": "42897",
    "pages_id": "15929",
    "seq_id": "31",
    "name": "Sphenoid Bone"
  },
  {
    "id": "42898",
    "pages_id": "15929",
    "seq_id": "32",
    "name": "Sphenoid Bone"
  },
  {
    "id": "42899",
    "pages_id": "15929",
    "seq_id": "33",
    "name": "Subdeltoid Bursa"
  },
  {
    "id": "42900",
    "pages_id": "15929",
    "seq_id": "34",
    "name": "Parietal Bone"
  },
  {
    "id": "42901",
    "pages_id": "15929",
    "seq_id": "35",
    "name": "T1 (1st Thoracic Vertebra)"
  },
  {
    "id": "42902",
    "pages_id": "15929",
    "seq_id": "36",
    "name": "Sphenoid Bone"
  },
  {
    "id": "42903",
    "pages_id": "15929",
    "seq_id": "37",
    "name": "Scapula"
  },
  {
    "id": "42904",
    "pages_id": "15929",
    "seq_id": "38",
    "name": "Subdeltoid Bursa"
  },
  {
    "id": "42905",
    "pages_id": "15929",
    "seq_id": "39",
    "name": "Occipital Bone"
  },
  {
    "id": "42906",
    "pages_id": "15929",
    "seq_id": "40",
    "name": "Nasal Bone"
  },
  {
    "id": "42907",
    "pages_id": "15929",
    "seq_id": "41",
    "name": "Maxillary Sinus"
  },
  {
    "id": "42908",
    "pages_id": "15929",
    "seq_id": "42",
    "name": "Intervertebral Discs"
  },
  {
    "id": "42909",
    "pages_id": "15929",
    "seq_id": "43",
    "name": "Intervertebral Discs"
  },
  {
    "id": "42910",
    "pages_id": "15929",
    "seq_id": "44",
    "name": "Intervertebral Discs"
  },
  {
    "id": "42911",
    "pages_id": "15929",
    "seq_id": "45",
    "name": "Lacrimal Bone"
  },
  {
    "id": "42912",
    "pages_id": "15929",
    "seq_id": "46",
    "name": "Intervertebral Discs"
  },
  {
    "id": "42913",
    "pages_id": "15929",
    "seq_id": "47",
    "name": "Mandible"
  },
  {
    "id": "42914",
    "pages_id": "15929",
    "seq_id": "48",
    "name": "Costoclavicular Ligament"
  },
  {
    "id": "42915",
    "pages_id": "15929",
    "seq_id": "49",
    "name": "Frontal Bone"
  },
  {
    "id": "42916",
    "pages_id": "15929",
    "seq_id": "50",
    "name": "Costal Cartilage"
  },
  {
    "id": "42917",
    "pages_id": "15929",
    "seq_id": "51",
    "name": "Subscapular Bursa to Shoulder Joint"
  },
  {
    "id": "42918",
    "pages_id": "15929",
    "seq_id": "52",
    "name": "Supraspinous Ligament"
  },
  {
    "id": "42919",
    "pages_id": "15929",
    "seq_id": "53",
    "name": "Sternum"
  },
  {
    "id": "42920",
    "pages_id": "15929",
    "seq_id": "54",
    "name": "Skull"
  },
  {
    "id": "42921",
    "pages_id": "15929",
    "seq_id": "55",
    "name": "Skull"
  },
  {
    "id": "42922",
    "pages_id": "15929",
    "seq_id": "56",
    "name": "Radiate Ligaments"
  },
  {
    "id": "42923",
    "pages_id": "15929",
    "seq_id": "57",
    "name": "Skull"
  },
  {
    "id": "42924",
    "pages_id": "15929",
    "seq_id": "58",
    "name": "Temporal Bone"
  },
  {
    "id": "42925",
    "pages_id": "15929",
    "seq_id": "59",
    "name": "Maxilla"
  },
  {
    "id": "42926",
    "pages_id": "15929",
    "seq_id": "60",
    "name": "Ethmoid Bone"
  },
  {
    "id": "42927",
    "pages_id": "15929",
    "seq_id": "61",
    "name": "Humerus"
  },
  {
    "id": "42928",
    "pages_id": "15929",
    "seq_id": "62",
    "name": "Hyoid Bone"
  },
  {
    "id": "42929",
    "pages_id": "15929",
    "seq_id": "63",
    "name": "Costoclavicular Ligament"
  },
  {
    "id": "42930",
    "pages_id": "15929",
    "seq_id": "64",
    "name": "Costal Cartilage"
  },
  {
    "id": "42931",
    "pages_id": "15929",
    "seq_id": "65",
    "name": "Clavicle"
  },
  {
    "id": "42932",
    "pages_id": "15929",
    "seq_id": "66",
    "name": "Clavicle"
  },
  {
    "id": "42933",
    "pages_id": "15929",
    "seq_id": "67",
    "name": "Capsular Ligament of the Shoulder"
  },
  {
    "id": "42934",
    "pages_id": "15929",
    "seq_id": "68",
    "name": "Conoid Ligament"
  },
  {
    "id": "42935",
    "pages_id": "15929",
    "seq_id": "69",
    "name": "Conoid Ligament"
  },
  {
    "id": "42936",
    "pages_id": "15929",
    "seq_id": "70",
    "name": "Trapezoid Ligament"
  },
  {
    "id": "42937",
    "pages_id": "15929",
    "seq_id": "71",
    "name": "Vomer"
  },
  {
    "id": "42938",
    "pages_id": "15929",
    "seq_id": "72",
    "name": "True Ribs"
  },
  {
    "id": "42939",
    "pages_id": "15929",
    "seq_id": "73",
    "name": "Transverse Ligament of Humerus"
  },
  {
    "id": "42940",
    "pages_id": "15929",
    "seq_id": "74",
    "name": "Trapezoid Ligament"
  },
  {
    "id": "42941",
    "pages_id": "15929",
    "seq_id": "75",
    "name": "Zygomatic Bone"
  },
  {
    "id": "42942",
    "pages_id": "15929",
    "seq_id": "76",
    "name": "True Ribs"
  },
  {
    "id": "42943",
    "pages_id": "15929",
    "seq_id": "77",
    "name": "True Ribs"
  },
  {
    "id": "42944",
    "pages_id": "15929",
    "seq_id": "78",
    "name": "True Ribs"
  },
  {
    "id": "42945",
    "pages_id": "15929",
    "seq_id": "79",
    "name": "True Ribs"
  },
  {
    "id": "42946",
    "pages_id": "15929",
    "seq_id": "80",
    "name": "True Ribs"
  },
  {
    "id": "42947",
    "pages_id": "15929",
    "seq_id": "81",
    "name": "True Ribs"
  },
  {
    "id": "42948",
    "pages_id": "15929",
    "seq_id": "82",
    "name": "Zygomatic Bone"
  },
  {
    "id": "42949",
    "pages_id": "15929",
    "seq_id": "83",
    "name": "True Ribs"
  },
  {
    "id": "42950",
    "pages_id": "15929",
    "seq_id": "84",
    "name": "True Ribs"
  },
  {
    "id": "42951",
    "pages_id": "15929",
    "seq_id": "85",
    "name": "Subscapular Bursa to Shoulder Joint"
  },
  {
    "id": "42952",
    "pages_id": "15929",
    "seq_id": "86",
    "name": "Supraspinous Ligament"
  },
  {
    "id": "42953",
    "pages_id": "15929",
    "seq_id": "87",
    "name": "Coracohumeral Ligament"
  },
  {
    "id": "42954",
    "pages_id": "15929",
    "seq_id": "88",
    "name": "Radiate Ligaments"
  },
  {
    "id": "42955",
    "pages_id": "15929",
    "seq_id": "89",
    "name": "Maxilla"
  },
  {
    "id": "42956",
    "pages_id": "15929",
    "seq_id": "90",
    "name": "Intertransverse Ligaments"
  },
  {
    "id": "42957",
    "pages_id": "15929",
    "seq_id": "91",
    "name": "Coracoacromial Ligament"
  },
  {
    "id": "42958",
    "pages_id": "15929",
    "seq_id": "92",
    "name": "Capsular Ligament of the Shoulder"
  },
  {
    "id": "42959",
    "pages_id": "15929",
    "seq_id": "93",
    "name": "Scapula"
  },
  {
    "id": "42960",
    "pages_id": "15929",
    "seq_id": "94",
    "name": "Scapula"
  },
  {
    "id": "42961",
    "pages_id": "15929",
    "seq_id": "95",
    "name": "Scapula"
  },
  {
    "id": "42962",
    "pages_id": "15929",
    "seq_id": "96",
    "name": "Scapula"
  },
  {
    "id": "42963",
    "pages_id": "15929",
    "seq_id": "97",
    "name": "Scapula"
  },
  {
    "id": "42964",
    "pages_id": "15929",
    "seq_id": "98",
    "name": "Scapula"
  },
  {
    "id": "42965",
    "pages_id": "15929",
    "seq_id": "99",
    "name": "Scapula"
  },
  {
    "id": "42966",
    "pages_id": "15929",
    "seq_id": "100",
    "name": "T1 (1st Thoracic Vertebra)"
  },
  {
    "id": "42967",
    "pages_id": "15929",
    "seq_id": "101",
    "name": "T1 (1st Thoracic Vertebra)"
  },
  {
    "id": "42968",
    "pages_id": "15929",
    "seq_id": "102",
    "name": "Scapula"
  },
  {
    "id": "42969",
    "pages_id": "15929",
    "seq_id": "103",
    "name": "Skull"
  },
  {
    "id": "42970",
    "pages_id": "15929",
    "seq_id": "104",
    "name": "Radiate Ligaments"
  },
  {
    "id": "42971",
    "pages_id": "15929",
    "seq_id": "105",
    "name": "Radiate Ligaments"
  },
  {
    "id": "42972",
    "pages_id": "15929",
    "seq_id": "106",
    "name": "Skull"
  },
  {
    "id": "42973",
    "pages_id": "15929",
    "seq_id": "107",
    "name": "Intervertebral Discs"
  },
  {
    "id": "42974",
    "pages_id": "15929",
    "seq_id": "108",
    "name": "Intervertebral Discs"
  },
  {
    "id": "42975",
    "pages_id": "15929",
    "seq_id": "109",
    "name": "Intertransverse Ligaments"
  },
  {
    "id": "42976",
    "pages_id": "15929",
    "seq_id": "110",
    "name": "Intervertebral Discs"
  },
  {
    "id": "42977",
    "pages_id": "15929",
    "seq_id": "111",
    "name": "Intertransverse Ligaments"
  },
  {
    "id": "42978",
    "pages_id": "15929",
    "seq_id": "112",
    "name": "Intervertebral Discs"
  },
  {
    "id": "42979",
    "pages_id": "15929",
    "seq_id": "113",
    "name": "Interclavicular Ligament"
  },
  {
    "id": "42980",
    "pages_id": "15929",
    "seq_id": "114",
    "name": "Temporal Bone"
  },
  {
    "id": "42981",
    "pages_id": "15929",
    "seq_id": "115",
    "name": "Temporal Bone"
  },
  {
    "id": "42982",
    "pages_id": "15929",
    "seq_id": "116",
    "name": "Temporal Bone"
  },
  {
    "id": "42983",
    "pages_id": "15929",
    "seq_id": "117",
    "name": "Temporal Bone"
  },
  {
    "id": "42984",
    "pages_id": "15929",
    "seq_id": "118",
    "name": "Temporal Bone"
  },
  {
    "id": "42985",
    "pages_id": "15929",
    "seq_id": "119",
    "name": "Radiate Ligaments"
  },
  {
    "id": "42986",
    "pages_id": "15929",
    "seq_id": "120",
    "name": "T1 (1st Thoracic Vertebra)"
  },
  {
    "id": "42987",
    "pages_id": "15929",
    "seq_id": "121",
    "name": "T1 (1st Thoracic Vertebra)"
  },
  {
    "id": "42988",
    "pages_id": "15929",
    "seq_id": "122",
    "name": "T1 (1st Thoracic Vertebra)"
  },
  {
    "id": "42989",
    "pages_id": "15929",
    "seq_id": "123",
    "name": "T2 (2nd Thoracic Vertebra)"
  },
  {
    "id": "42990",
    "pages_id": "15929",
    "seq_id": "124",
    "name": "T1 (1st Thoracic Vertebra)"
  },
  {
    "id": "42991",
    "pages_id": "15929",
    "seq_id": "125",
    "name": "T3 (3rd Thoracic Vertebra)"
  },
  {
    "id": "42992",
    "pages_id": "15929",
    "seq_id": "126",
    "name": "T2 (2nd Thoracic Vertebra)"
  }
]