[
  {
    "pages_id": "12",
    "seq_id": "1",
    "name": "Anconeus Muscle",
    "id": "893"
  },
  {
    "pages_id": "12",
    "seq_id": "2",
    "name": "Brachioradialis Muscle",
    "id": "894"
  },
  {
    "pages_id": "12",
    "seq_id": "3",
    "name": "Extensor Carpi Radialis Brevis Muscle",
    "id": "895"
  },
  {
    "pages_id": "12",
    "seq_id": "4",
    "name": "Extensor Carpi Radialis Longus Muscle",
    "id": "896"
  },
  {
    "pages_id": "12",
    "seq_id": "5",
    "name": "Flexor Carpi Ulnaris Muscle",
    "id": "897"
  },
  {
    "pages_id": "12",
    "seq_id": "6",
    "name": "Flexor Digitorum Superficialis Muscle",
    "id": "898"
  },
  {
    "pages_id": "12",
    "seq_id": "7",
    "name": "Flexor Digitorum Superficialis Muscle",
    "id": "899"
  },
  {
    "pages_id": "12",
    "seq_id": "8",
    "name": "Flexor Digitorum Superficialis Muscle",
    "id": "900"
  },
  {
    "pages_id": "12",
    "seq_id": "9",
    "name": "Humerus",
    "id": "901"
  },
  {
    "pages_id": "12",
    "seq_id": "10",
    "name": "Humerus",
    "id": "902"
  },
  {
    "pages_id": "12",
    "seq_id": "11",
    "name": "Joint Capsule of Elbow",
    "id": "903"
  },
  {
    "pages_id": "12",
    "seq_id": "12",
    "name": "Joint Capsule of Elbow",
    "id": "904"
  },
  {
    "pages_id": "12",
    "seq_id": "13",
    "name": "Joint Capsule of Elbow",
    "id": "905"
  },
  {
    "pages_id": "12",
    "seq_id": "14",
    "name": "Palmaris Longus Muscle",
    "id": "906"
  },
  {
    "pages_id": "12",
    "seq_id": "15",
    "name": "Palmaris Longus Muscle",
    "id": "907"
  },
  {
    "pages_id": "12",
    "seq_id": "16",
    "name": "Radial Collateral Ligament of Elbow",
    "id": "908"
  },
  {
    "pages_id": "12",
    "seq_id": "17",
    "name": "Supinator Muscle",
    "id": "909"
  },
  {
    "pages_id": "12",
    "seq_id": "18",
    "name": "Supinator Muscle",
    "id": "910"
  },
  {
    "pages_id": "12",
    "seq_id": "19",
    "name": "Triceps Brachii Muscle (Medial Head)",
    "id": "911"
  },
  {
    "pages_id": "12",
    "seq_id": "20",
    "name": "Triceps Brachii Muscle (Medial Head)",
    "id": "912"
  },
  {
    "pages_id": "12",
    "seq_id": "21",
    "name": "Triceps Brachii Tendon",
    "id": "913"
  },
  {
    "pages_id": "12",
    "seq_id": "22",
    "name": "Ulna",
    "id": "914"
  },
  {
    "pages_id": "12",
    "seq_id": "23",
    "name": "Ulnar Collateral Ligament of Elbow",
    "id": "915"
  },
  {
    "pages_id": "12",
    "seq_id": "24",
    "name": "Ulnar Collateral Ligament of Elbow",
    "id": "916"
  },
  {
    "pages_id": "12",
    "seq_id": "25",
    "name": "Gluteus Medius Muscle",
    "id": "917"
  },
  {
    "pages_id": "12",
    "seq_id": "26",
    "name": "Pelvis",
    "id": "918"
  }
]