[
  {
    "pages_id": "405",
    "seq_id": "1",
    "name": "Esophagus",
    "id": "21708"
  },
  {
    "pages_id": "405",
    "seq_id": "2",
    "name": "Gallbladder",
    "id": "21709"
  },
  {
    "pages_id": "405",
    "seq_id": "3",
    "name": "Large Intestine",
    "id": "21710"
  },
  {
    "pages_id": "405",
    "seq_id": "4",
    "name": "Large Intestine",
    "id": "21711"
  },
  {
    "pages_id": "405",
    "seq_id": "5",
    "name": "Large Intestine",
    "id": "21712"
  },
  {
    "pages_id": "405",
    "seq_id": "6",
    "name": "Liver",
    "id": "21713"
  },
  {
    "pages_id": "405",
    "seq_id": "7",
    "name": "Pancreas",
    "id": "21714"
  },
  {
    "pages_id": "405",
    "seq_id": "8",
    "name": "Spleen",
    "id": "21715"
  },
  {
    "pages_id": "405",
    "seq_id": "9",
    "name": "Spleen",
    "id": "21716"
  },
  {
    "pages_id": "405",
    "seq_id": "10",
    "name": "Stomach",
    "id": "21717"
  },
  {
    "pages_id": "405",
    "seq_id": "11",
    "name": "Small Intestine",
    "id": "21718"
  }
]