[
  {
    "id": "13111",
    "pages_id": "11879",
    "seq_id": "1",
    "name": "Dorsal Digital Arteries of Foot"
  },
  {
    "id": "13112",
    "pages_id": "11879",
    "seq_id": "2",
    "name": "Dorsal Digital Arteries of Foot"
  },
  {
    "id": "13113",
    "pages_id": "11879",
    "seq_id": "3",
    "name": "Dorsal Digital Arteries of Foot"
  },
  {
    "id": "13114",
    "pages_id": "11879",
    "seq_id": "4",
    "name": "Dorsal Venous Arch of Foot"
  },
  {
    "id": "13115",
    "pages_id": "11879",
    "seq_id": "5",
    "name": "Palmar Digital Arteries"
  },
  {
    "id": "13116",
    "pages_id": "11879",
    "seq_id": "6",
    "name": "Dorsal Metatarsal Veins"
  },
  {
    "id": "13117",
    "pages_id": "11879",
    "seq_id": "7",
    "name": "Dorsal Metatarsal Veins"
  },
  {
    "id": "13118",
    "pages_id": "11879",
    "seq_id": "8",
    "name": "Dorsal Metatarsal Veins"
  },
  {
    "id": "13119",
    "pages_id": "11879",
    "seq_id": "9",
    "name": "Dorsal Metatarsal Veins"
  },
  {
    "id": "13120",
    "pages_id": "11879",
    "seq_id": "10",
    "name": "Dorsal Metatarsal Veins"
  },
  {
    "id": "13121",
    "pages_id": "11879",
    "seq_id": "11",
    "name": "Dorsal Metatarsal Veins"
  },
  {
    "id": "13122",
    "pages_id": "11879",
    "seq_id": "12",
    "name": "Dorsal Metatarsal Veins"
  },
  {
    "id": "13123",
    "pages_id": "11879",
    "seq_id": "13",
    "name": "Dorsal Metatarsal Veins"
  },
  {
    "id": "13124",
    "pages_id": "11879",
    "seq_id": "14",
    "name": "Dorsal Metatarsal Veins"
  },
  {
    "id": "13125",
    "pages_id": "11879",
    "seq_id": "15",
    "name": "Dorsal Metatarsal Arteries"
  },
  {
    "id": "13126",
    "pages_id": "11879",
    "seq_id": "16",
    "name": "Dorsal Metatarsal Arteries"
  },
  {
    "id": "13127",
    "pages_id": "11879",
    "seq_id": "17",
    "name": "Dorsal Metatarsal Arteries"
  },
  {
    "id": "13128",
    "pages_id": "11879",
    "seq_id": "18",
    "name": "Dorsal Metatarsal Arteries"
  },
  {
    "id": "13129",
    "pages_id": "11879",
    "seq_id": "19",
    "name": "Dorsal Metatarsal Arteries"
  },
  {
    "id": "13130",
    "pages_id": "11879",
    "seq_id": "20",
    "name": "Dorsal Metatarsal Arteries"
  },
  {
    "id": "13131",
    "pages_id": "11879",
    "seq_id": "21",
    "name": "Dorsal Metatarsal Arteries"
  },
  {
    "id": "13132",
    "pages_id": "11879",
    "seq_id": "22",
    "name": "Dorsal Metatarsal Arteries"
  },
  {
    "id": "13133",
    "pages_id": "11879",
    "seq_id": "23",
    "name": "Dorsal Digital Arteries of Foot"
  },
  {
    "id": "13134",
    "pages_id": "11879",
    "seq_id": "24",
    "name": "Anterior Tibial Vein"
  },
  {
    "id": "13135",
    "pages_id": "11879",
    "seq_id": "25",
    "name": "Anterior Tibial Vein"
  },
  {
    "id": "13136",
    "pages_id": "11879",
    "seq_id": "26",
    "name": "Anterior Tibial Vein"
  },
  {
    "id": "13137",
    "pages_id": "11879",
    "seq_id": "27",
    "name": "Anterior Tibial Vein"
  },
  {
    "id": "13138",
    "pages_id": "11879",
    "seq_id": "28",
    "name": "Anterior Tibial Vein"
  },
  {
    "id": "13139",
    "pages_id": "11879",
    "seq_id": "29",
    "name": "Intermediate Antebrachial Vein"
  },
  {
    "id": "13140",
    "pages_id": "11879",
    "seq_id": "30",
    "name": "Intermediate Antebrachial Vein"
  },
  {
    "id": "13141",
    "pages_id": "11879",
    "seq_id": "31",
    "name": "Internal Iliac Artery"
  },
  {
    "id": "13142",
    "pages_id": "11879",
    "seq_id": "32",
    "name": "Internal Iliac Artery"
  },
  {
    "id": "13143",
    "pages_id": "11879",
    "seq_id": "33",
    "name": "Internal Iliac Artery"
  },
  {
    "id": "13144",
    "pages_id": "11879",
    "seq_id": "34",
    "name": "Internal Iliac Vein"
  },
  {
    "id": "13145",
    "pages_id": "11879",
    "seq_id": "35",
    "name": "Internal Iliac Vein"
  },
  {
    "id": "13146",
    "pages_id": "11879",
    "seq_id": "36",
    "name": "Intestinal Veins"
  },
  {
    "id": "13147",
    "pages_id": "11879",
    "seq_id": "37",
    "name": "Intestinal Veins"
  },
  {
    "id": "13148",
    "pages_id": "11879",
    "seq_id": "38",
    "name": "Intestinal Veins"
  },
  {
    "id": "13149",
    "pages_id": "11879",
    "seq_id": "39",
    "name": "Intestinal Veins"
  },
  {
    "id": "13150",
    "pages_id": "11879",
    "seq_id": "40",
    "name": "Intestinal Veins"
  },
  {
    "id": "13151",
    "pages_id": "11879",
    "seq_id": "41",
    "name": "Intestinal Veins"
  },
  {
    "id": "13152",
    "pages_id": "11879",
    "seq_id": "42",
    "name": "Intestinal Veins"
  },
  {
    "id": "13153",
    "pages_id": "11879",
    "seq_id": "43",
    "name": "Lateral Circumflex Femoral Artery"
  },
  {
    "id": "13154",
    "pages_id": "11879",
    "seq_id": "44",
    "name": "Lateral Circumflex Femoral Artery"
  },
  {
    "id": "13155",
    "pages_id": "11879",
    "seq_id": "45",
    "name": "Lateral Superior Genicular Artery"
  },
  {
    "id": "13156",
    "pages_id": "11879",
    "seq_id": "46",
    "name": "Medial Inferior Genicular Artery"
  },
  {
    "id": "13157",
    "pages_id": "11879",
    "seq_id": "47",
    "name": "Lateral Superior Genicular Artery"
  },
  {
    "id": "13158",
    "pages_id": "11879",
    "seq_id": "48",
    "name": "Palmar Digital Arteries"
  },
  {
    "id": "13159",
    "pages_id": "11879",
    "seq_id": "49",
    "name": "Palmar Digital Arteries"
  },
  {
    "id": "13160",
    "pages_id": "11879",
    "seq_id": "50",
    "name": "Palmar Digital Arteries"
  },
  {
    "id": "13161",
    "pages_id": "11879",
    "seq_id": "51",
    "name": "Palmar Digital Arteries"
  },
  {
    "id": "13162",
    "pages_id": "11879",
    "seq_id": "52",
    "name": "Palmar Digital Arteries"
  },
  {
    "id": "13163",
    "pages_id": "11879",
    "seq_id": "53",
    "name": "Palmar Digital Arteries"
  },
  {
    "id": "13164",
    "pages_id": "11879",
    "seq_id": "54",
    "name": "Palmar Digital Arteries"
  },
  {
    "id": "13165",
    "pages_id": "11879",
    "seq_id": "55",
    "name": "Palmar Digital Arteries"
  },
  {
    "id": "13166",
    "pages_id": "11879",
    "seq_id": "56",
    "name": "Palmar Digital Arteries"
  },
  {
    "id": "13167",
    "pages_id": "11879",
    "seq_id": "57",
    "name": "Palmar Digital Arteries"
  },
  {
    "id": "13168",
    "pages_id": "11879",
    "seq_id": "58",
    "name": "Palmar Digital Arteries"
  },
  {
    "id": "13169",
    "pages_id": "11879",
    "seq_id": "59",
    "name": "Palmar Digital Arteries"
  },
  {
    "id": "13170",
    "pages_id": "11879",
    "seq_id": "60",
    "name": "Palmar Digital Arteries"
  },
  {
    "id": "13171",
    "pages_id": "11879",
    "seq_id": "61",
    "name": "Palmar Digital Arteries"
  },
  {
    "id": "13172",
    "pages_id": "11879",
    "seq_id": "62",
    "name": "Palmar Digital Arteries"
  },
  {
    "id": "13173",
    "pages_id": "11879",
    "seq_id": "63",
    "name": "Palmar Digital Arteries"
  },
  {
    "id": "13174",
    "pages_id": "11879",
    "seq_id": "64",
    "name": "Palmar Digital Arteries"
  },
  {
    "id": "13175",
    "pages_id": "11879",
    "seq_id": "65",
    "name": "Palmar Digital Arteries"
  },
  {
    "id": "13176",
    "pages_id": "11879",
    "seq_id": "66",
    "name": "Ulnar Artery"
  },
  {
    "id": "13177",
    "pages_id": "11879",
    "seq_id": "67",
    "name": "Arcuate Artery"
  },
  {
    "id": "13178",
    "pages_id": "11879",
    "seq_id": "68",
    "name": "Arcuate Artery"
  },
  {
    "id": "13179",
    "pages_id": "11879",
    "seq_id": "69",
    "name": "Anterior Tibial Vein"
  },
  {
    "id": "13180",
    "pages_id": "11879",
    "seq_id": "70",
    "name": "Arcuate Artery"
  },
  {
    "id": "13181",
    "pages_id": "11879",
    "seq_id": "71",
    "name": "Arcuate Artery"
  },
  {
    "id": "13182",
    "pages_id": "11879",
    "seq_id": "72",
    "name": "Deep Femoral Artery (Profunda Femoris)"
  },
  {
    "id": "13183",
    "pages_id": "11879",
    "seq_id": "73",
    "name": "Anterior Tibial Vein"
  },
  {
    "id": "13184",
    "pages_id": "11879",
    "seq_id": "74",
    "name": "Arcuate Artery"
  },
  {
    "id": "13185",
    "pages_id": "11879",
    "seq_id": "75",
    "name": "Palmar Digital Arteries"
  },
  {
    "id": "13186",
    "pages_id": "11879",
    "seq_id": "76",
    "name": "Palmar Digital Arteries"
  },
  {
    "id": "13187",
    "pages_id": "11879",
    "seq_id": "77",
    "name": "Palmar Digital Arteries"
  },
  {
    "id": "13188",
    "pages_id": "11879",
    "seq_id": "78",
    "name": "Palmar Digital Arteries"
  },
  {
    "id": "13189",
    "pages_id": "11879",
    "seq_id": "79",
    "name": "Palmar Digital Arteries"
  },
  {
    "id": "13190",
    "pages_id": "11879",
    "seq_id": "80",
    "name": "Palmar Digital Arteries"
  },
  {
    "id": "13191",
    "pages_id": "11879",
    "seq_id": "81",
    "name": "Palmar Digital Arteries"
  },
  {
    "id": "13192",
    "pages_id": "11879",
    "seq_id": "82",
    "name": "Palmar Digital Arteries"
  },
  {
    "id": "13193",
    "pages_id": "11879",
    "seq_id": "83",
    "name": "Palmar Digital Arteries"
  },
  {
    "id": "13194",
    "pages_id": "11879",
    "seq_id": "84",
    "name": "Palmar Digital Arteries"
  },
  {
    "id": "13195",
    "pages_id": "11879",
    "seq_id": "85",
    "name": "Palmar Digital Arteries"
  },
  {
    "id": "13196",
    "pages_id": "11879",
    "seq_id": "86",
    "name": "Palmar Digital Arteries"
  },
  {
    "id": "13197",
    "pages_id": "11879",
    "seq_id": "87",
    "name": "Anterior Tibial Artery"
  },
  {
    "id": "13198",
    "pages_id": "11879",
    "seq_id": "88",
    "name": "Ulnar Artery"
  },
  {
    "id": "13199",
    "pages_id": "11879",
    "seq_id": "89",
    "name": "Ulnar Artery"
  },
  {
    "id": "13200",
    "pages_id": "11879",
    "seq_id": "90",
    "name": "Ulnar Artery"
  },
  {
    "id": "13201",
    "pages_id": "11879",
    "seq_id": "91",
    "name": "Dorsal Digital Arteries of Foot"
  },
  {
    "id": "13202",
    "pages_id": "11879",
    "seq_id": "92",
    "name": "Deep Femoral Artery (Profunda Femoris)"
  },
  {
    "id": "13203",
    "pages_id": "11879",
    "seq_id": "93",
    "name": "Arcuate Artery"
  },
  {
    "id": "13204",
    "pages_id": "11879",
    "seq_id": "94",
    "name": "Arcuate Artery"
  },
  {
    "id": "13205",
    "pages_id": "11879",
    "seq_id": "95",
    "name": "Anterior Tibial Vein"
  },
  {
    "id": "13206",
    "pages_id": "11879",
    "seq_id": "96",
    "name": "Arcuate Artery"
  },
  {
    "id": "13207",
    "pages_id": "11879",
    "seq_id": "97",
    "name": "Dorsal Digital Arteries of Foot"
  },
  {
    "id": "13208",
    "pages_id": "11879",
    "seq_id": "98",
    "name": "Dorsal Digital Arteries of Foot"
  },
  {
    "id": "13209",
    "pages_id": "11879",
    "seq_id": "99",
    "name": "Dorsal Digital Arteries of Foot"
  },
  {
    "id": "13210",
    "pages_id": "11879",
    "seq_id": "100",
    "name": "Dorsal Digital Arteries of Foot"
  },
  {
    "id": "13211",
    "pages_id": "11879",
    "seq_id": "101",
    "name": "Dorsal Digital Arteries of Foot"
  },
  {
    "id": "13212",
    "pages_id": "11879",
    "seq_id": "102",
    "name": "Dorsal Digital Arteries of Foot"
  },
  {
    "id": "13213",
    "pages_id": "11879",
    "seq_id": "103",
    "name": "Dorsal Digital Arteries of Foot"
  },
  {
    "id": "13214",
    "pages_id": "11879",
    "seq_id": "104",
    "name": "Dorsal Digital Arteries of Foot"
  },
  {
    "id": "13215",
    "pages_id": "11879",
    "seq_id": "105",
    "name": "Dorsal Digital Arteries of Foot"
  },
  {
    "id": "13216",
    "pages_id": "11879",
    "seq_id": "106",
    "name": "Dorsal Digital Arteries of Foot"
  },
  {
    "id": "13217",
    "pages_id": "11879",
    "seq_id": "107",
    "name": "Dorsal Digital Arteries of Foot"
  },
  {
    "id": "13218",
    "pages_id": "11879",
    "seq_id": "108",
    "name": "Dorsal Digital Arteries of Foot"
  },
  {
    "id": "13219",
    "pages_id": "11879",
    "seq_id": "109",
    "name": "Dorsal Digital Arteries of Foot"
  },
  {
    "id": "13220",
    "pages_id": "11879",
    "seq_id": "110",
    "name": "Dorsal Digital Arteries of Foot"
  },
  {
    "id": "13221",
    "pages_id": "11879",
    "seq_id": "111",
    "name": "Dorsal Digital Veins of Foot"
  },
  {
    "id": "13222",
    "pages_id": "11879",
    "seq_id": "112",
    "name": "Dorsal Digital Veins of Foot"
  },
  {
    "id": "13223",
    "pages_id": "11879",
    "seq_id": "113",
    "name": "Dorsal Digital Veins of Foot"
  },
  {
    "id": "13224",
    "pages_id": "11879",
    "seq_id": "114",
    "name": "Dorsal Digital Veins of Foot"
  },
  {
    "id": "13225",
    "pages_id": "11879",
    "seq_id": "115",
    "name": "Dorsal Digital Veins of Foot"
  },
  {
    "id": "13226",
    "pages_id": "11879",
    "seq_id": "116",
    "name": "Dorsal Digital Veins of Foot"
  },
  {
    "id": "13227",
    "pages_id": "11879",
    "seq_id": "117",
    "name": "Dorsal Digital Veins of Foot"
  },
  {
    "id": "13228",
    "pages_id": "11879",
    "seq_id": "118",
    "name": "Dorsal Metatarsal Arteries"
  },
  {
    "id": "13229",
    "pages_id": "11879",
    "seq_id": "119",
    "name": "Dorsal Metatarsal Arteries"
  },
  {
    "id": "13230",
    "pages_id": "11879",
    "seq_id": "120",
    "name": "Dorsal Digital Veins of Foot"
  },
  {
    "id": "13231",
    "pages_id": "11879",
    "seq_id": "121",
    "name": "Anterior Tibial Artery"
  },
  {
    "id": "13232",
    "pages_id": "11879",
    "seq_id": "122",
    "name": "Anterior Tibial Artery"
  },
  {
    "id": "13233",
    "pages_id": "11879",
    "seq_id": "123",
    "name": "Anterior Tibial Artery"
  },
  {
    "id": "13234",
    "pages_id": "11879",
    "seq_id": "124",
    "name": "Dorsal Venous Arch of Foot"
  },
  {
    "id": "13235",
    "pages_id": "11879",
    "seq_id": "125",
    "name": "Dorsal Venous Arch of Foot"
  },
  {
    "id": "13236",
    "pages_id": "11879",
    "seq_id": "126",
    "name": "Dorsal Venous Arch of Foot"
  },
  {
    "id": "13237",
    "pages_id": "11879",
    "seq_id": "127",
    "name": "Dorsal Venous Arch of Foot"
  },
  {
    "id": "13238",
    "pages_id": "11879",
    "seq_id": "128",
    "name": "Dorsal Venous Arch of Foot"
  },
  {
    "id": "13239",
    "pages_id": "11879",
    "seq_id": "129",
    "name": "Dorsal Venous Arch of Foot"
  },
  {
    "id": "13240",
    "pages_id": "11879",
    "seq_id": "130",
    "name": "Dorsal Venous Network of Hand"
  },
  {
    "id": "13241",
    "pages_id": "11879",
    "seq_id": "131",
    "name": "Dorsal Venous Network of Hand"
  },
  {
    "id": "13242",
    "pages_id": "11879",
    "seq_id": "132",
    "name": "Dorsal Venous Arch of Foot"
  },
  {
    "id": "13243",
    "pages_id": "11879",
    "seq_id": "133",
    "name": "Dorsal Venous Network of Hand"
  },
  {
    "id": "13244",
    "pages_id": "11879",
    "seq_id": "134",
    "name": "Dorsal Venous Network of Hand"
  },
  {
    "id": "13245",
    "pages_id": "11879",
    "seq_id": "135",
    "name": "Dorsal Venous Network of Hand"
  },
  {
    "id": "13246",
    "pages_id": "11879",
    "seq_id": "136",
    "name": "Dorsal Venous Network of Hand"
  },
  {
    "id": "13247",
    "pages_id": "11879",
    "seq_id": "137",
    "name": "Dorsal Venous Network of Hand"
  },
  {
    "id": "13248",
    "pages_id": "11879",
    "seq_id": "138",
    "name": "Dorsal Venous Network of Hand"
  },
  {
    "id": "13249",
    "pages_id": "11879",
    "seq_id": "139",
    "name": "Dorsal Venous Network of Hand"
  },
  {
    "id": "13250",
    "pages_id": "11879",
    "seq_id": "140",
    "name": "Dorsal Venous Network of Hand"
  },
  {
    "id": "13251",
    "pages_id": "11879",
    "seq_id": "141",
    "name": "Anterior Tibial Artery"
  },
  {
    "id": "13252",
    "pages_id": "11879",
    "seq_id": "142",
    "name": "Anterior Tibial Artery"
  },
  {
    "id": "13253",
    "pages_id": "11879",
    "seq_id": "143",
    "name": "External Iliac Artery"
  },
  {
    "id": "13254",
    "pages_id": "11879",
    "seq_id": "144",
    "name": "External Iliac Artery"
  },
  {
    "id": "13255",
    "pages_id": "11879",
    "seq_id": "145",
    "name": "External Iliac Artery"
  },
  {
    "id": "13256",
    "pages_id": "11879",
    "seq_id": "146",
    "name": "External Iliac Vein"
  },
  {
    "id": "13257",
    "pages_id": "11879",
    "seq_id": "147",
    "name": "External Iliac Vein"
  },
  {
    "id": "13258",
    "pages_id": "11879",
    "seq_id": "148",
    "name": "Femoral Artery"
  },
  {
    "id": "13259",
    "pages_id": "11879",
    "seq_id": "149",
    "name": "External Iliac Vein"
  },
  {
    "id": "13260",
    "pages_id": "11879",
    "seq_id": "150",
    "name": "Femoral Artery"
  },
  {
    "id": "13261",
    "pages_id": "11879",
    "seq_id": "151",
    "name": "Femoral Artery"
  },
  {
    "id": "13262",
    "pages_id": "11879",
    "seq_id": "152",
    "name": "Femoral Artery"
  },
  {
    "id": "13263",
    "pages_id": "11879",
    "seq_id": "153",
    "name": "Femoral Artery"
  },
  {
    "id": "13264",
    "pages_id": "11879",
    "seq_id": "154",
    "name": "Femoral Artery"
  },
  {
    "id": "13265",
    "pages_id": "11879",
    "seq_id": "155",
    "name": "Femoral Artery"
  },
  {
    "id": "13266",
    "pages_id": "11879",
    "seq_id": "156",
    "name": "Femoral Artery"
  },
  {
    "id": "13267",
    "pages_id": "11879",
    "seq_id": "157",
    "name": "Femoral Artery"
  },
  {
    "id": "13268",
    "pages_id": "11879",
    "seq_id": "158",
    "name": "Femoral Artery"
  },
  {
    "id": "13269",
    "pages_id": "11879",
    "seq_id": "159",
    "name": "Femoral Vein"
  },
  {
    "id": "13270",
    "pages_id": "11879",
    "seq_id": "160",
    "name": "Femoral Vein"
  },
  {
    "id": "13271",
    "pages_id": "11879",
    "seq_id": "161",
    "name": "Femoral Vein"
  },
  {
    "id": "13272",
    "pages_id": "11879",
    "seq_id": "162",
    "name": "Femoral Vein"
  },
  {
    "id": "13273",
    "pages_id": "11879",
    "seq_id": "163",
    "name": "Femoral Vein"
  },
  {
    "id": "13274",
    "pages_id": "11879",
    "seq_id": "164",
    "name": "Femoral Vein"
  },
  {
    "id": "13275",
    "pages_id": "11879",
    "seq_id": "165",
    "name": "Femoral Vein"
  },
  {
    "id": "13276",
    "pages_id": "11879",
    "seq_id": "166",
    "name": "Femoral Vein"
  },
  {
    "id": "13277",
    "pages_id": "11879",
    "seq_id": "167",
    "name": "Great Saphenous Vein"
  },
  {
    "id": "13278",
    "pages_id": "11879",
    "seq_id": "168",
    "name": "Great Saphenous Vein"
  },
  {
    "id": "13279",
    "pages_id": "11879",
    "seq_id": "169",
    "name": "Internal Iliac Vein"
  },
  {
    "id": "13280",
    "pages_id": "11879",
    "seq_id": "170",
    "name": "Intestinal Veins"
  },
  {
    "id": "13281",
    "pages_id": "11879",
    "seq_id": "171",
    "name": "Intestinal Veins"
  },
  {
    "id": "13282",
    "pages_id": "11879",
    "seq_id": "172",
    "name": "Intestinal Veins"
  },
  {
    "id": "13283",
    "pages_id": "11879",
    "seq_id": "173",
    "name": "Lateral Circumflex Femoral Vein"
  },
  {
    "id": "13284",
    "pages_id": "11879",
    "seq_id": "174",
    "name": "Lateral Circumflex Femoral Artery"
  },
  {
    "id": "13285",
    "pages_id": "11879",
    "seq_id": "175",
    "name": "Lateral Circumflex Femoral Artery"
  },
  {
    "id": "13286",
    "pages_id": "11879",
    "seq_id": "176",
    "name": "Lateral Circumflex Femoral Vein"
  },
  {
    "id": "13287",
    "pages_id": "11879",
    "seq_id": "177",
    "name": "Lateral Circumflex Femoral Vein"
  },
  {
    "id": "13288",
    "pages_id": "11879",
    "seq_id": "178",
    "name": "Lateral Circumflex Femoral Vein"
  },
  {
    "id": "13289",
    "pages_id": "11879",
    "seq_id": "179",
    "name": "Lateral Circumflex Femoral Vein"
  },
  {
    "id": "13290",
    "pages_id": "11879",
    "seq_id": "180",
    "name": "Lateral Circumflex Femoral Vein"
  },
  {
    "id": "13291",
    "pages_id": "11879",
    "seq_id": "181",
    "name": "Lateral Circumflex Femoral Vein"
  },
  {
    "id": "13292",
    "pages_id": "11879",
    "seq_id": "182",
    "name": "Lateral Circumflex Femoral Vein"
  },
  {
    "id": "13293",
    "pages_id": "11879",
    "seq_id": "183",
    "name": "Lateral Circumflex Femoral Vein"
  },
  {
    "id": "13294",
    "pages_id": "11879",
    "seq_id": "184",
    "name": "Lateral Inferior Genicular Artery"
  },
  {
    "id": "13295",
    "pages_id": "11879",
    "seq_id": "185",
    "name": "Lateral Circumflex Femoral Vein"
  },
  {
    "id": "13296",
    "pages_id": "11879",
    "seq_id": "186",
    "name": "Lateral Inferior Genicular Artery"
  },
  {
    "id": "13297",
    "pages_id": "11879",
    "seq_id": "187",
    "name": "Medial Inferior Genicular Artery"
  },
  {
    "id": "13298",
    "pages_id": "11879",
    "seq_id": "188",
    "name": "Medial Inferior Genicular Artery"
  },
  {
    "id": "13299",
    "pages_id": "11879",
    "seq_id": "189",
    "name": "Medial Superior Genicular Artery"
  },
  {
    "id": "13300",
    "pages_id": "11879",
    "seq_id": "190",
    "name": "Medial Superior Genicular Artery"
  },
  {
    "id": "13301",
    "pages_id": "11879",
    "seq_id": "191",
    "name": "Medial Superior Genicular Artery"
  },
  {
    "id": "13302",
    "pages_id": "11879",
    "seq_id": "192",
    "name": "Medial Superior Genicular Artery"
  },
  {
    "id": "13303",
    "pages_id": "11879",
    "seq_id": "193",
    "name": "Palmar Digital Arteries"
  },
  {
    "id": "13304",
    "pages_id": "11879",
    "seq_id": "194",
    "name": "Palmar Digital Arteries"
  },
  {
    "id": "13305",
    "pages_id": "11879",
    "seq_id": "195",
    "name": "Palmar Digital Arteries"
  },
  {
    "id": "13306",
    "pages_id": "11879",
    "seq_id": "196",
    "name": "Palmar Digital Arteries"
  },
  {
    "id": "13307",
    "pages_id": "11879",
    "seq_id": "197",
    "name": "Palmar Digital Arteries"
  },
  {
    "id": "13308",
    "pages_id": "11879",
    "seq_id": "198",
    "name": "Palmar Digital Arteries"
  },
  {
    "id": "13309",
    "pages_id": "11879",
    "seq_id": "199",
    "name": "Palmar Digital Arteries"
  },
  {
    "id": "13310",
    "pages_id": "11879",
    "seq_id": "200",
    "name": "Palmar Digital Arteries"
  },
  {
    "id": "13311",
    "pages_id": "11879",
    "seq_id": "201",
    "name": "Palmar Digital Arteries"
  },
  {
    "id": "13312",
    "pages_id": "11879",
    "seq_id": "202",
    "name": "Palmar Digital Arteries"
  },
  {
    "id": "13313",
    "pages_id": "11879",
    "seq_id": "203",
    "name": "Palmar Digital Arteries"
  },
  {
    "id": "13314",
    "pages_id": "11879",
    "seq_id": "204",
    "name": "Palmar Digital Arteries"
  },
  {
    "id": "13315",
    "pages_id": "11879",
    "seq_id": "205",
    "name": "Palmar Digital Arteries"
  },
  {
    "id": "13316",
    "pages_id": "11879",
    "seq_id": "206",
    "name": "Palmar Digital Arteries"
  },
  {
    "id": "13317",
    "pages_id": "11879",
    "seq_id": "207",
    "name": "Palmar Digital Arteries"
  },
  {
    "id": "13318",
    "pages_id": "11879",
    "seq_id": "208",
    "name": "Palmar Digital Arteries"
  },
  {
    "id": "13319",
    "pages_id": "11879",
    "seq_id": "209",
    "name": "Palmar Digital Arteries"
  },
  {
    "id": "13320",
    "pages_id": "11879",
    "seq_id": "210",
    "name": "Palmar Digital Arteries"
  },
  {
    "id": "13321",
    "pages_id": "11879",
    "seq_id": "211",
    "name": "Palmar Digital Arteries"
  },
  {
    "id": "13322",
    "pages_id": "11879",
    "seq_id": "212",
    "name": "Palmar Digital Arteries"
  },
  {
    "id": "13323",
    "pages_id": "11879",
    "seq_id": "213",
    "name": "Palmar Digital Arteries"
  },
  {
    "id": "13324",
    "pages_id": "11879",
    "seq_id": "214",
    "name": "Palmar Digital Arteries"
  },
  {
    "id": "13325",
    "pages_id": "11879",
    "seq_id": "215",
    "name": "Palmar Digital Arteries"
  },
  {
    "id": "13326",
    "pages_id": "11879",
    "seq_id": "216",
    "name": "Palmar Digital Arteries"
  },
  {
    "id": "13327",
    "pages_id": "11879",
    "seq_id": "217",
    "name": "Palmar Digital Arteries"
  },
  {
    "id": "13328",
    "pages_id": "11879",
    "seq_id": "218",
    "name": "Palmar Digital Arteries"
  },
  {
    "id": "13329",
    "pages_id": "11879",
    "seq_id": "219",
    "name": "Palmar Digital Arteries"
  },
  {
    "id": "13330",
    "pages_id": "11879",
    "seq_id": "220",
    "name": "Palmar Digital Arteries"
  },
  {
    "id": "13331",
    "pages_id": "11879",
    "seq_id": "221",
    "name": "Palmar Digital Arteries"
  },
  {
    "id": "13332",
    "pages_id": "11879",
    "seq_id": "222",
    "name": "Palmar Digital Arteries"
  },
  {
    "id": "13333",
    "pages_id": "11879",
    "seq_id": "223",
    "name": "Radial Artery"
  },
  {
    "id": "13334",
    "pages_id": "11879",
    "seq_id": "224",
    "name": "Radial Artery"
  },
  {
    "id": "13335",
    "pages_id": "11879",
    "seq_id": "225",
    "name": "Radial Artery"
  },
  {
    "id": "13336",
    "pages_id": "11879",
    "seq_id": "226",
    "name": "Radial Artery"
  },
  {
    "id": "13337",
    "pages_id": "11879",
    "seq_id": "227",
    "name": "Superficial Palmar Arterial Arch"
  },
  {
    "id": "13338",
    "pages_id": "11879",
    "seq_id": "228",
    "name": "Superficial Palmar Arterial Arch"
  },
  {
    "id": "13339",
    "pages_id": "11879",
    "seq_id": "229",
    "name": "Superficial Palmar Arterial Arch"
  },
  {
    "id": "13340",
    "pages_id": "11879",
    "seq_id": "230",
    "name": "Superficial Palmar Arterial Arch"
  },
  {
    "id": "13341",
    "pages_id": "11879",
    "seq_id": "231",
    "name": "Anterior Tibial Artery"
  },
  {
    "id": "13342",
    "pages_id": "11879",
    "seq_id": "232",
    "name": "Anterior Tibial Artery"
  },
  {
    "id": "13343",
    "pages_id": "11879",
    "seq_id": "233",
    "name": "Deep Femoral Vein (Profunda Femoris)"
  },
  {
    "id": "13344",
    "pages_id": "11879",
    "seq_id": "234",
    "name": "Anterior Tibial Artery"
  },
  {
    "id": "13345",
    "pages_id": "11879",
    "seq_id": "235",
    "name": "Deep Femoral Vein (Profunda Femoris)"
  },
  {
    "id": "13346",
    "pages_id": "11879",
    "seq_id": "236",
    "name": "Deep Femoral Vein (Profunda Femoris)"
  },
  {
    "id": "13347",
    "pages_id": "11879",
    "seq_id": "237",
    "name": "Deep Femoral Vein (Profunda Femoris)"
  },
  {
    "id": "13348",
    "pages_id": "11879",
    "seq_id": "238",
    "name": "Deep Femoral Vein (Profunda Femoris)"
  },
  {
    "id": "13349",
    "pages_id": "11879",
    "seq_id": "239",
    "name": "Deep Femoral Vein (Profunda Femoris)"
  },
  {
    "id": "13350",
    "pages_id": "11879",
    "seq_id": "240",
    "name": "Dorsal Metatarsal Arteries"
  },
  {
    "id": "13351",
    "pages_id": "11879",
    "seq_id": "241",
    "name": "Dorsal Metatarsal Arteries"
  },
  {
    "id": "13352",
    "pages_id": "11879",
    "seq_id": "242",
    "name": "Dorsal Metatarsal Arteries"
  },
  {
    "id": "13353",
    "pages_id": "11879",
    "seq_id": "243",
    "name": "Dorsal Metatarsal Arteries"
  },
  {
    "id": "13354",
    "pages_id": "11879",
    "seq_id": "244",
    "name": "Dorsal Metatarsal Arteries"
  },
  {
    "id": "13355",
    "pages_id": "11879",
    "seq_id": "245",
    "name": "Dorsal Metatarsal Arteries"
  },
  {
    "id": "13356",
    "pages_id": "11879",
    "seq_id": "246",
    "name": "Dorsal Metatarsal Arteries"
  },
  {
    "id": "13357",
    "pages_id": "11879",
    "seq_id": "247",
    "name": "Dorsal Metatarsal Arteries"
  }
]