[
  {
    "id": "15918",
    "pages_id": "11905",
    "seq_id": "1",
    "name": "Aorta"
  },
  {
    "id": "15919",
    "pages_id": "11905",
    "seq_id": "2",
    "name": "Aorta"
  },
  {
    "id": "15920",
    "pages_id": "11905",
    "seq_id": "3",
    "name": "Aorta"
  },
  {
    "id": "15921",
    "pages_id": "11905",
    "seq_id": "4",
    "name": "Aorta"
  },
  {
    "id": "15922",
    "pages_id": "11905",
    "seq_id": "5",
    "name": "Aorta"
  },
  {
    "id": "15923",
    "pages_id": "11905",
    "seq_id": "6",
    "name": "Aorta"
  },
  {
    "id": "15924",
    "pages_id": "11905",
    "seq_id": "7",
    "name": "Aorta"
  },
  {
    "id": "15925",
    "pages_id": "11905",
    "seq_id": "8",
    "name": "Aorta"
  },
  {
    "id": "15926",
    "pages_id": "11905",
    "seq_id": "9",
    "name": "Aorta"
  },
  {
    "id": "15927",
    "pages_id": "11905",
    "seq_id": "10",
    "name": "Aorta"
  },
  {
    "id": "15928",
    "pages_id": "11905",
    "seq_id": "11",
    "name": "Aorta"
  },
  {
    "id": "15929",
    "pages_id": "11905",
    "seq_id": "12",
    "name": "Aorta"
  },
  {
    "id": "15930",
    "pages_id": "11905",
    "seq_id": "13",
    "name": "Aorta"
  },
  {
    "id": "15931",
    "pages_id": "11905",
    "seq_id": "14",
    "name": "Aorta"
  },
  {
    "id": "15932",
    "pages_id": "11905",
    "seq_id": "15",
    "name": "Aorta"
  },
  {
    "id": "15933",
    "pages_id": "11905",
    "seq_id": "16",
    "name": "Aorta"
  },
  {
    "id": "15934",
    "pages_id": "11905",
    "seq_id": "17",
    "name": "Aorta"
  },
  {
    "id": "15935",
    "pages_id": "11905",
    "seq_id": "18",
    "name": "Aorta"
  },
  {
    "id": "15936",
    "pages_id": "11905",
    "seq_id": "19",
    "name": "Aorta"
  },
  {
    "id": "15937",
    "pages_id": "11905",
    "seq_id": "20",
    "name": "Aorta"
  },
  {
    "id": "15938",
    "pages_id": "11905",
    "seq_id": "21",
    "name": "Aorta"
  },
  {
    "id": "15939",
    "pages_id": "11905",
    "seq_id": "22",
    "name": "Aorta"
  },
  {
    "id": "15940",
    "pages_id": "11905",
    "seq_id": "23",
    "name": "Aorta"
  },
  {
    "id": "15941",
    "pages_id": "11905",
    "seq_id": "24",
    "name": "Aorta"
  },
  {
    "id": "15942",
    "pages_id": "11905",
    "seq_id": "25",
    "name": "Aorta"
  },
  {
    "id": "15943",
    "pages_id": "11905",
    "seq_id": "26",
    "name": "Aorta"
  },
  {
    "id": "15944",
    "pages_id": "11905",
    "seq_id": "27",
    "name": "Aorta"
  },
  {
    "id": "15945",
    "pages_id": "11905",
    "seq_id": "28",
    "name": "Aorta"
  },
  {
    "id": "15946",
    "pages_id": "11905",
    "seq_id": "29",
    "name": "Aorta"
  },
  {
    "id": "15947",
    "pages_id": "11905",
    "seq_id": "30",
    "name": "Aorta"
  },
  {
    "id": "15948",
    "pages_id": "11905",
    "seq_id": "31",
    "name": "Aorta"
  },
  {
    "id": "15949",
    "pages_id": "11905",
    "seq_id": "32",
    "name": "Aorta"
  },
  {
    "id": "15950",
    "pages_id": "11905",
    "seq_id": "33",
    "name": "Aorta"
  },
  {
    "id": "15951",
    "pages_id": "11905",
    "seq_id": "34",
    "name": "Aorta"
  },
  {
    "id": "15952",
    "pages_id": "11905",
    "seq_id": "35",
    "name": "Brachiocephalic Trunk"
  },
  {
    "id": "15953",
    "pages_id": "11905",
    "seq_id": "36",
    "name": "Heart"
  },
  {
    "id": "15954",
    "pages_id": "11905",
    "seq_id": "37",
    "name": "Heart"
  },
  {
    "id": "15955",
    "pages_id": "11905",
    "seq_id": "38",
    "name": "Inferior Vena Cava"
  },
  {
    "id": "15956",
    "pages_id": "11905",
    "seq_id": "39",
    "name": "Inferior Vena Cava"
  },
  {
    "id": "15957",
    "pages_id": "11905",
    "seq_id": "40",
    "name": "Inferior Vena Cava"
  },
  {
    "id": "15958",
    "pages_id": "11905",
    "seq_id": "41",
    "name": "Inferior Vena Cava"
  },
  {
    "id": "15959",
    "pages_id": "11905",
    "seq_id": "42",
    "name": "Inferior Vena Cava"
  },
  {
    "id": "15960",
    "pages_id": "11905",
    "seq_id": "43",
    "name": "Inferior Vena Cava"
  },
  {
    "id": "15961",
    "pages_id": "11905",
    "seq_id": "44",
    "name": "Inferior Vena Cava"
  },
  {
    "id": "15962",
    "pages_id": "11905",
    "seq_id": "45",
    "name": "Inferior Vena Cava"
  },
  {
    "id": "15963",
    "pages_id": "11905",
    "seq_id": "46",
    "name": "Inferior Vena Cava"
  },
  {
    "id": "15964",
    "pages_id": "11905",
    "seq_id": "47",
    "name": "Inferior Vena Cava"
  },
  {
    "id": "15965",
    "pages_id": "11905",
    "seq_id": "48",
    "name": "Inferior Vena Cava"
  },
  {
    "id": "15966",
    "pages_id": "11905",
    "seq_id": "49",
    "name": "Inferior Vena Cava"
  },
  {
    "id": "15967",
    "pages_id": "11905",
    "seq_id": "50",
    "name": "Inferior Vena Cava"
  },
  {
    "id": "15968",
    "pages_id": "11905",
    "seq_id": "51",
    "name": "Inferior Vena Cava"
  },
  {
    "id": "15969",
    "pages_id": "11905",
    "seq_id": "52",
    "name": "Inferior Vena Cava"
  },
  {
    "id": "15970",
    "pages_id": "11905",
    "seq_id": "53",
    "name": "Inferior Vena Cava"
  },
  {
    "id": "15971",
    "pages_id": "11905",
    "seq_id": "54",
    "name": "Inferior Vena Cava"
  },
  {
    "id": "15972",
    "pages_id": "11905",
    "seq_id": "55",
    "name": "Inferior Vena Cava"
  },
  {
    "id": "15973",
    "pages_id": "11905",
    "seq_id": "56",
    "name": "Inferior Vena Cava"
  },
  {
    "id": "15974",
    "pages_id": "11905",
    "seq_id": "57",
    "name": "Inferior Vena Cava"
  },
  {
    "id": "15975",
    "pages_id": "11905",
    "seq_id": "58",
    "name": "Inferior Vena Cava"
  },
  {
    "id": "15976",
    "pages_id": "11905",
    "seq_id": "59",
    "name": "Inferior Vena Cava"
  },
  {
    "id": "15977",
    "pages_id": "11905",
    "seq_id": "60",
    "name": "Inferior Vena Cava"
  },
  {
    "id": "15978",
    "pages_id": "11905",
    "seq_id": "61",
    "name": "Inferior Vena Cava"
  },
  {
    "id": "15979",
    "pages_id": "11905",
    "seq_id": "62",
    "name": "Inferior Vena Cava"
  },
  {
    "id": "15980",
    "pages_id": "11905",
    "seq_id": "63",
    "name": "Inferior Vena Cava"
  },
  {
    "id": "15981",
    "pages_id": "11905",
    "seq_id": "64",
    "name": "Inferior Vena Cava"
  },
  {
    "id": "15982",
    "pages_id": "11905",
    "seq_id": "65",
    "name": "Inferior Vena Cava"
  },
  {
    "id": "15983",
    "pages_id": "11905",
    "seq_id": "66",
    "name": "Inferior Vena Cava"
  },
  {
    "id": "15984",
    "pages_id": "11905",
    "seq_id": "67",
    "name": "Inferior Vena Cava"
  },
  {
    "id": "15985",
    "pages_id": "11905",
    "seq_id": "68",
    "name": "Inferior Vena Cava"
  },
  {
    "id": "15986",
    "pages_id": "11905",
    "seq_id": "69",
    "name": "Inferior Vena Cava"
  },
  {
    "id": "15987",
    "pages_id": "11905",
    "seq_id": "70",
    "name": "Inferior Vena Cava"
  },
  {
    "id": "15988",
    "pages_id": "11905",
    "seq_id": "71",
    "name": "Inferior Vena Cava"
  },
  {
    "id": "15989",
    "pages_id": "11905",
    "seq_id": "72",
    "name": "Inferior Vena Cava"
  },
  {
    "id": "15990",
    "pages_id": "11905",
    "seq_id": "73",
    "name": "Left Subclavian Artery"
  },
  {
    "id": "15991",
    "pages_id": "11905",
    "seq_id": "74",
    "name": "Left Subclavian Artery"
  },
  {
    "id": "15992",
    "pages_id": "11905",
    "seq_id": "75",
    "name": "Left Subclavian Artery"
  },
  {
    "id": "15993",
    "pages_id": "11905",
    "seq_id": "76",
    "name": "Left Subclavian Vein"
  },
  {
    "id": "15994",
    "pages_id": "11905",
    "seq_id": "77",
    "name": "Left Brachiocephalic Vein"
  },
  {
    "id": "15995",
    "pages_id": "11905",
    "seq_id": "78",
    "name": "Left Common Carotid Artery"
  },
  {
    "id": "15996",
    "pages_id": "11905",
    "seq_id": "79",
    "name": "Left Common Carotid Artery"
  },
  {
    "id": "15997",
    "pages_id": "11905",
    "seq_id": "80",
    "name": "Left External Jugular Vein"
  },
  {
    "id": "15998",
    "pages_id": "11905",
    "seq_id": "81",
    "name": "Left Internal Jugular Vein"
  },
  {
    "id": "15999",
    "pages_id": "11905",
    "seq_id": "82",
    "name": "Right Internal Jugular Vein"
  },
  {
    "id": "16000",
    "pages_id": "11905",
    "seq_id": "83",
    "name": "Right External Jugular Vein"
  },
  {
    "id": "16001",
    "pages_id": "11905",
    "seq_id": "84",
    "name": "Right Brachiocephalic Vein"
  },
  {
    "id": "16002",
    "pages_id": "11905",
    "seq_id": "85",
    "name": "Right Common Carotid Artery"
  },
  {
    "id": "16003",
    "pages_id": "11905",
    "seq_id": "86",
    "name": "Right Subclavian Artery"
  },
  {
    "id": "16004",
    "pages_id": "11905",
    "seq_id": "87",
    "name": "Right Subclavian Artery"
  },
  {
    "id": "16005",
    "pages_id": "11905",
    "seq_id": "88",
    "name": "Right Subclavian Artery"
  },
  {
    "id": "16006",
    "pages_id": "11905",
    "seq_id": "89",
    "name": "Right Subclavian Vein"
  },
  {
    "id": "16007",
    "pages_id": "11905",
    "seq_id": "90",
    "name": "Superior Vena Cava"
  },
  {
    "id": "16008",
    "pages_id": "11905",
    "seq_id": "91",
    "name": "Superior Vena Cava"
  }
]