[
  {
    "pages_id": "336",
    "seq_id": "1",
    "name": "Hepatic Portal Vein",
    "id": "16425"
  },
  {
    "pages_id": "336",
    "seq_id": "2",
    "name": "Splenic Artery",
    "id": "16426"
  },
  {
    "pages_id": "336",
    "seq_id": "3",
    "name": "Splenic Artery",
    "id": "16427"
  },
  {
    "pages_id": "336",
    "seq_id": "4",
    "name": "Splenic Artery",
    "id": "16428"
  },
  {
    "pages_id": "336",
    "seq_id": "5",
    "name": "Splenic Artery",
    "id": "16429"
  },
  {
    "pages_id": "336",
    "seq_id": "6",
    "name": "Splenic Vein",
    "id": "16430"
  },
  {
    "pages_id": "336",
    "seq_id": "7",
    "name": "Splenic Vein",
    "id": "16431"
  },
  {
    "pages_id": "336",
    "seq_id": "8",
    "name": "Splenic Vein",
    "id": "16432"
  },
  {
    "pages_id": "336",
    "seq_id": "9",
    "name": "Right Gastric Vein",
    "id": "16433"
  },
  {
    "pages_id": "336",
    "seq_id": "10",
    "name": "Splenic Artery",
    "id": "16434"
  },
  {
    "pages_id": "336",
    "seq_id": "11",
    "name": "Right Gastric Artery",
    "id": "16435"
  },
  {
    "pages_id": "336",
    "seq_id": "12",
    "name": "Left Gastric Artery",
    "id": "16436"
  },
  {
    "pages_id": "336",
    "seq_id": "13",
    "name": "Hepatic Veins",
    "id": "16437"
  },
  {
    "pages_id": "336",
    "seq_id": "14",
    "name": "Hepatic Veins",
    "id": "16438"
  },
  {
    "pages_id": "336",
    "seq_id": "15",
    "name": "Inferior Vena Cava",
    "id": "16439"
  },
  {
    "pages_id": "336",
    "seq_id": "16",
    "name": "Inferior Vena Cava",
    "id": "16440"
  },
  {
    "pages_id": "336",
    "seq_id": "17",
    "name": "Inferior Vena Cava",
    "id": "16441"
  },
  {
    "pages_id": "336",
    "seq_id": "18",
    "name": "Inferior Vena Cava",
    "id": "16442"
  },
  {
    "pages_id": "336",
    "seq_id": "19",
    "name": "Inferior Vena Cava",
    "id": "16443"
  },
  {
    "pages_id": "336",
    "seq_id": "20",
    "name": "Inferior Vena Cava",
    "id": "16444"
  },
  {
    "pages_id": "336",
    "seq_id": "21",
    "name": "Inferior Vena Cava",
    "id": "16445"
  },
  {
    "pages_id": "336",
    "seq_id": "22",
    "name": "Inferior Vena Cava",
    "id": "16446"
  },
  {
    "pages_id": "336",
    "seq_id": "23",
    "name": "Inferior Vena Cava",
    "id": "16447"
  },
  {
    "pages_id": "336",
    "seq_id": "24",
    "name": "Inferior Vena Cava",
    "id": "16448"
  },
  {
    "pages_id": "336",
    "seq_id": "25",
    "name": "Inferior Vena Cava",
    "id": "16449"
  },
  {
    "pages_id": "336",
    "seq_id": "26",
    "name": "Inferior Vena Cava",
    "id": "16450"
  },
  {
    "pages_id": "336",
    "seq_id": "27",
    "name": "Inferior Vena Cava",
    "id": "16451"
  },
  {
    "pages_id": "336",
    "seq_id": "28",
    "name": "Inferior Vena Cava",
    "id": "16452"
  },
  {
    "pages_id": "336",
    "seq_id": "29",
    "name": "Inferior Vena Cava",
    "id": "16453"
  },
  {
    "pages_id": "336",
    "seq_id": "30",
    "name": "Inferior Vena Cava",
    "id": "16454"
  },
  {
    "pages_id": "336",
    "seq_id": "31",
    "name": "Inferior Vena Cava",
    "id": "16455"
  },
  {
    "pages_id": "336",
    "seq_id": "32",
    "name": "Inferior Vena Cava",
    "id": "16456"
  },
  {
    "pages_id": "336",
    "seq_id": "33",
    "name": "Inferior Vena Cava",
    "id": "16457"
  },
  {
    "pages_id": "336",
    "seq_id": "34",
    "name": "Left Gastric Artery",
    "id": "16458"
  },
  {
    "pages_id": "336",
    "seq_id": "35",
    "name": "Right Gastric Artery",
    "id": "16459"
  },
  {
    "pages_id": "336",
    "seq_id": "36",
    "name": "Inferior Vena Cava",
    "id": "16460"
  },
  {
    "pages_id": "336",
    "seq_id": "37",
    "name": "Proper Hepatic Artery",
    "id": "16461"
  },
  {
    "pages_id": "336",
    "seq_id": "38",
    "name": "Left Hepatic Artery",
    "id": "16462"
  },
  {
    "pages_id": "336",
    "seq_id": "39",
    "name": "Right Hepatic Artery",
    "id": "16463"
  },
  {
    "pages_id": "336",
    "seq_id": "40",
    "name": "Proper Hepatic Artery",
    "id": "16464"
  },
  {
    "pages_id": "336",
    "seq_id": "41",
    "name": "Splenic Vein",
    "id": "16465"
  },
  {
    "pages_id": "336",
    "seq_id": "42",
    "name": "Right Hepatic Artery",
    "id": "16466"
  },
  {
    "pages_id": "336",
    "seq_id": "43",
    "name": "Inferior Vena Cava",
    "id": "16467"
  },
  {
    "pages_id": "336",
    "seq_id": "44",
    "name": "Right Hepatic Artery",
    "id": "16468"
  },
  {
    "pages_id": "336",
    "seq_id": "45",
    "name": "Right Hepatic Artery",
    "id": "16469"
  },
  {
    "pages_id": "336",
    "seq_id": "46",
    "name": "Right Hepatic Artery",
    "id": "16470"
  },
  {
    "pages_id": "336",
    "seq_id": "47",
    "name": "Abdominal Aorta",
    "id": "16471"
  },
  {
    "pages_id": "336",
    "seq_id": "48",
    "name": "Abdominal Aorta",
    "id": "16472"
  },
  {
    "pages_id": "336",
    "seq_id": "49",
    "name": "Abdominal Aorta",
    "id": "16473"
  },
  {
    "pages_id": "336",
    "seq_id": "50",
    "name": "Abdominal Aorta",
    "id": "16474"
  },
  {
    "pages_id": "336",
    "seq_id": "51",
    "name": "Hepatic Portal Vein",
    "id": "16475"
  },
  {
    "pages_id": "336",
    "seq_id": "52",
    "name": "Abdominal Aorta",
    "id": "16476"
  },
  {
    "pages_id": "336",
    "seq_id": "53",
    "name": "Common Hepatic Artery",
    "id": "16477"
  },
  {
    "pages_id": "336",
    "seq_id": "54",
    "name": "Abdominal Aorta",
    "id": "16478"
  },
  {
    "pages_id": "336",
    "seq_id": "55",
    "name": "Celiac Artery (Celiac Trunk)",
    "id": "16479"
  },
  {
    "pages_id": "336",
    "seq_id": "56",
    "name": "Hepatic Portal Vein",
    "id": "16480"
  },
  {
    "pages_id": "336",
    "seq_id": "57",
    "name": "Hepatic Portal Vein",
    "id": "16481"
  },
  {
    "pages_id": "336",
    "seq_id": "58",
    "name": "Hepatic Portal Vein",
    "id": "16482"
  },
  {
    "pages_id": "336",
    "seq_id": "59",
    "name": "Hepatic Portal Vein",
    "id": "16483"
  },
  {
    "pages_id": "336",
    "seq_id": "60",
    "name": "Hepatic Portal Vein",
    "id": "16484"
  },
  {
    "pages_id": "336",
    "seq_id": "61",
    "name": "Hepatic Portal Vein",
    "id": "16485"
  },
  {
    "pages_id": "336",
    "seq_id": "62",
    "name": "Hepatic Portal Vein",
    "id": "16486"
  },
  {
    "pages_id": "336",
    "seq_id": "63",
    "name": "Hepatic Portal Vein",
    "id": "16487"
  },
  {
    "pages_id": "336",
    "seq_id": "64",
    "name": "Hepatic Portal Vein",
    "id": "16488"
  },
  {
    "pages_id": "336",
    "seq_id": "65",
    "name": "Hepatic Portal Vein",
    "id": "16489"
  },
  {
    "pages_id": "336",
    "seq_id": "66",
    "name": "Hepatic Portal Vein",
    "id": "16490"
  },
  {
    "pages_id": "336",
    "seq_id": "67",
    "name": "Hepatic Portal Vein",
    "id": "16491"
  },
  {
    "pages_id": "336",
    "seq_id": "68",
    "name": "Hepatic Portal Vein",
    "id": "16492"
  },
  {
    "pages_id": "336",
    "seq_id": "69",
    "name": "Hepatic Portal Vein",
    "id": "16493"
  },
  {
    "pages_id": "336",
    "seq_id": "70",
    "name": "Hepatic Portal Vein",
    "id": "16494"
  },
  {
    "pages_id": "336",
    "seq_id": "71",
    "name": "Hepatic Portal Vein",
    "id": "16495"
  },
  {
    "pages_id": "336",
    "seq_id": "72",
    "name": "Hepatic Portal Vein",
    "id": "16496"
  },
  {
    "pages_id": "336",
    "seq_id": "73",
    "name": "Hepatic Portal Vein",
    "id": "16497"
  },
  {
    "pages_id": "336",
    "seq_id": "74",
    "name": "Hepatic Portal Vein",
    "id": "16498"
  },
  {
    "pages_id": "336",
    "seq_id": "75",
    "name": "Hepatic Portal Vein",
    "id": "16499"
  },
  {
    "pages_id": "336",
    "seq_id": "76",
    "name": "Hepatic Portal Vein",
    "id": "16500"
  },
  {
    "pages_id": "336",
    "seq_id": "77",
    "name": "Hepatic Portal Vein",
    "id": "16501"
  },
  {
    "pages_id": "336",
    "seq_id": "78",
    "name": "Hepatic Portal Vein",
    "id": "16502"
  },
  {
    "pages_id": "336",
    "seq_id": "79",
    "name": "Hepatic Portal Vein",
    "id": "16503"
  },
  {
    "pages_id": "336",
    "seq_id": "80",
    "name": "Hepatic Portal Vein",
    "id": "16504"
  },
  {
    "pages_id": "336",
    "seq_id": "81",
    "name": "Hepatic Portal Vein",
    "id": "16505"
  },
  {
    "pages_id": "336",
    "seq_id": "82",
    "name": "Hepatic Veins",
    "id": "16506"
  },
  {
    "pages_id": "336",
    "seq_id": "83",
    "name": "Hepatic Veins",
    "id": "16507"
  },
  {
    "pages_id": "336",
    "seq_id": "84",
    "name": "Hepatic Veins",
    "id": "16508"
  },
  {
    "pages_id": "336",
    "seq_id": "85",
    "name": "Hepatic Veins",
    "id": "16509"
  },
  {
    "pages_id": "336",
    "seq_id": "86",
    "name": "Hepatic Veins",
    "id": "16510"
  },
  {
    "pages_id": "336",
    "seq_id": "87",
    "name": "Hepatic Veins",
    "id": "16511"
  },
  {
    "pages_id": "336",
    "seq_id": "88",
    "name": "Inferior Vena Cava",
    "id": "16512"
  },
  {
    "pages_id": "336",
    "seq_id": "89",
    "name": "Hepatic Veins",
    "id": "16513"
  },
  {
    "pages_id": "336",
    "seq_id": "90",
    "name": "Hepatic Veins",
    "id": "16514"
  },
  {
    "pages_id": "336",
    "seq_id": "91",
    "name": "Inferior Vena Cava",
    "id": "16515"
  },
  {
    "pages_id": "336",
    "seq_id": "92",
    "name": "Inferior Vena Cava",
    "id": "16516"
  },
  {
    "pages_id": "336",
    "seq_id": "93",
    "name": "Inferior Vena Cava",
    "id": "16517"
  },
  {
    "pages_id": "336",
    "seq_id": "94",
    "name": "Inferior Vena Cava",
    "id": "16518"
  },
  {
    "pages_id": "336",
    "seq_id": "95",
    "name": "Inferior Vena Cava",
    "id": "16519"
  },
  {
    "pages_id": "336",
    "seq_id": "96",
    "name": "Inferior Vena Cava",
    "id": "16520"
  },
  {
    "pages_id": "336",
    "seq_id": "97",
    "name": "Inferior Vena Cava",
    "id": "16521"
  },
  {
    "pages_id": "336",
    "seq_id": "98",
    "name": "Inferior Vena Cava",
    "id": "16522"
  },
  {
    "pages_id": "336",
    "seq_id": "99",
    "name": "Inferior Vena Cava",
    "id": "16523"
  },
  {
    "pages_id": "336",
    "seq_id": "100",
    "name": "Inferior Vena Cava",
    "id": "16524"
  },
  {
    "pages_id": "336",
    "seq_id": "101",
    "name": "Inferior Vena Cava",
    "id": "16525"
  },
  {
    "pages_id": "336",
    "seq_id": "102",
    "name": "Inferior Vena Cava",
    "id": "16526"
  },
  {
    "pages_id": "336",
    "seq_id": "103",
    "name": "Inferior Vena Cava",
    "id": "16527"
  },
  {
    "pages_id": "336",
    "seq_id": "104",
    "name": "Inferior Vena Cava",
    "id": "16528"
  },
  {
    "pages_id": "336",
    "seq_id": "105",
    "name": "Inferior Vena Cava",
    "id": "16529"
  },
  {
    "pages_id": "336",
    "seq_id": "106",
    "name": "Right Gastric Artery",
    "id": "16530"
  },
  {
    "pages_id": "336",
    "seq_id": "107",
    "name": "Left Gastric Artery",
    "id": "16531"
  },
  {
    "pages_id": "336",
    "seq_id": "108",
    "name": "Right Gastric Artery",
    "id": "16532"
  },
  {
    "pages_id": "336",
    "seq_id": "109",
    "name": "Left Gastric Artery",
    "id": "16533"
  },
  {
    "pages_id": "336",
    "seq_id": "110",
    "name": "Left Gastric Artery",
    "id": "16534"
  },
  {
    "pages_id": "336",
    "seq_id": "111",
    "name": "Left Gastric Artery",
    "id": "16535"
  },
  {
    "pages_id": "336",
    "seq_id": "112",
    "name": "Left Gastric Artery",
    "id": "16536"
  },
  {
    "pages_id": "336",
    "seq_id": "113",
    "name": "Left Gastric Artery",
    "id": "16537"
  },
  {
    "pages_id": "336",
    "seq_id": "114",
    "name": "Left Hepatic Artery",
    "id": "16538"
  },
  {
    "pages_id": "336",
    "seq_id": "115",
    "name": "Splenic Vein",
    "id": "16539"
  },
  {
    "pages_id": "336",
    "seq_id": "116",
    "name": "Right Hepatic Artery",
    "id": "16540"
  },
  {
    "pages_id": "336",
    "seq_id": "117",
    "name": "Splenic Vein",
    "id": "16541"
  },
  {
    "pages_id": "336",
    "seq_id": "118",
    "name": "Splenic Artery",
    "id": "16542"
  },
  {
    "pages_id": "336",
    "seq_id": "119",
    "name": "Abdominal Aorta",
    "id": "16543"
  },
  {
    "pages_id": "336",
    "seq_id": "120",
    "name": "Abdominal Aorta",
    "id": "16544"
  },
  {
    "pages_id": "336",
    "seq_id": "121",
    "name": "Abdominal Aorta",
    "id": "16545"
  },
  {
    "pages_id": "336",
    "seq_id": "122",
    "name": "Abdominal Aorta",
    "id": "16546"
  },
  {
    "pages_id": "336",
    "seq_id": "123",
    "name": "Abdominal Aorta",
    "id": "16547"
  },
  {
    "pages_id": "336",
    "seq_id": "124",
    "name": "Abdominal Aorta",
    "id": "16548"
  },
  {
    "pages_id": "336",
    "seq_id": "125",
    "name": "Abdominal Aorta",
    "id": "16549"
  },
  {
    "pages_id": "336",
    "seq_id": "126",
    "name": "Abdominal Aorta",
    "id": "16550"
  },
  {
    "pages_id": "336",
    "seq_id": "127",
    "name": "Abdominal Aorta",
    "id": "16551"
  },
  {
    "pages_id": "336",
    "seq_id": "128",
    "name": "Abdominal Aorta",
    "id": "16552"
  },
  {
    "pages_id": "336",
    "seq_id": "129",
    "name": "Abdominal Aorta",
    "id": "16553"
  },
  {
    "pages_id": "336",
    "seq_id": "130",
    "name": "Abdominal Aorta",
    "id": "16554"
  },
  {
    "pages_id": "336",
    "seq_id": "131",
    "name": "Abdominal Aorta",
    "id": "16555"
  },
  {
    "pages_id": "336",
    "seq_id": "132",
    "name": "Abdominal Aorta",
    "id": "16556"
  },
  {
    "pages_id": "336",
    "seq_id": "133",
    "name": "Abdominal Aorta",
    "id": "16557"
  },
  {
    "pages_id": "336",
    "seq_id": "134",
    "name": "Abdominal Aorta",
    "id": "16558"
  },
  {
    "pages_id": "336",
    "seq_id": "135",
    "name": "Abdominal Aorta",
    "id": "16559"
  },
  {
    "pages_id": "336",
    "seq_id": "136",
    "name": "Abdominal Aorta",
    "id": "16560"
  },
  {
    "pages_id": "336",
    "seq_id": "137",
    "name": "Abdominal Aorta",
    "id": "16561"
  },
  {
    "pages_id": "336",
    "seq_id": "138",
    "name": "Abdominal Aorta",
    "id": "16562"
  },
  {
    "pages_id": "336",
    "seq_id": "139",
    "name": "Abdominal Aorta",
    "id": "16563"
  },
  {
    "pages_id": "336",
    "seq_id": "140",
    "name": "Abdominal Aorta",
    "id": "16564"
  },
  {
    "pages_id": "336",
    "seq_id": "141",
    "name": "Abdominal Aorta",
    "id": "16565"
  },
  {
    "pages_id": "336",
    "seq_id": "142",
    "name": "Abdominal Aorta",
    "id": "16566"
  },
  {
    "pages_id": "336",
    "seq_id": "143",
    "name": "Abdominal Aorta",
    "id": "16567"
  },
  {
    "pages_id": "336",
    "seq_id": "144",
    "name": "Splenic Vein",
    "id": "16568"
  }
]