[
  {
    "id": "41997",
    "pages_id": "15918",
    "seq_id": "1",
    "name": "Mandible"
  },
  {
    "id": "41998",
    "pages_id": "15918",
    "seq_id": "2",
    "name": "Parietal Bone"
  },
  {
    "id": "41999",
    "pages_id": "15918",
    "seq_id": "3",
    "name": "Parietal Bone"
  },
  {
    "id": "42000",
    "pages_id": "15918",
    "seq_id": "4",
    "name": "Frontal Bone"
  },
  {
    "id": "42001",
    "pages_id": "15918",
    "seq_id": "5",
    "name": "Frontal Bone"
  },
  {
    "id": "42002",
    "pages_id": "15918",
    "seq_id": "6",
    "name": "Frontal Bone"
  },
  {
    "id": "42003",
    "pages_id": "15918",
    "seq_id": "7",
    "name": "Frontal Bone"
  },
  {
    "id": "42004",
    "pages_id": "15918",
    "seq_id": "8",
    "name": "Frontal Bone"
  },
  {
    "id": "42005",
    "pages_id": "15918",
    "seq_id": "9",
    "name": "Frontal Bone"
  },
  {
    "id": "42006",
    "pages_id": "15918",
    "seq_id": "10",
    "name": "Frontal Bone"
  },
  {
    "id": "42007",
    "pages_id": "15918",
    "seq_id": "11",
    "name": "Frontal Bone"
  },
  {
    "id": "42008",
    "pages_id": "15918",
    "seq_id": "12",
    "name": "Teeth"
  },
  {
    "id": "42009",
    "pages_id": "15918",
    "seq_id": "13",
    "name": "Teeth"
  },
  {
    "id": "42010",
    "pages_id": "15918",
    "seq_id": "14",
    "name": "Teeth"
  },
  {
    "id": "42011",
    "pages_id": "15918",
    "seq_id": "15",
    "name": "Sphenoid Bone"
  },
  {
    "id": "42012",
    "pages_id": "15918",
    "seq_id": "16",
    "name": "Occipital Bone"
  },
  {
    "id": "42013",
    "pages_id": "15918",
    "seq_id": "17",
    "name": "Sphenoid Bone"
  },
  {
    "id": "42014",
    "pages_id": "15918",
    "seq_id": "18",
    "name": "Sphenoid Bone"
  },
  {
    "id": "42015",
    "pages_id": "15918",
    "seq_id": "19",
    "name": "Sphenoid Bone"
  },
  {
    "id": "42016",
    "pages_id": "15918",
    "seq_id": "20",
    "name": "Sphenoid Bone"
  },
  {
    "id": "42017",
    "pages_id": "15918",
    "seq_id": "21",
    "name": "Teeth"
  },
  {
    "id": "42018",
    "pages_id": "15918",
    "seq_id": "22",
    "name": "Hyoid Bone"
  },
  {
    "id": "42019",
    "pages_id": "15918",
    "seq_id": "23",
    "name": "Parietal Bone"
  },
  {
    "id": "42020",
    "pages_id": "15918",
    "seq_id": "24",
    "name": "Parietal Bone"
  },
  {
    "id": "42021",
    "pages_id": "15918",
    "seq_id": "25",
    "name": "Parietal Bone"
  },
  {
    "id": "42022",
    "pages_id": "15918",
    "seq_id": "26",
    "name": "Temporal Bone"
  },
  {
    "id": "42023",
    "pages_id": "15918",
    "seq_id": "27",
    "name": "Temporal Bone"
  },
  {
    "id": "42024",
    "pages_id": "15918",
    "seq_id": "28",
    "name": "Temporal Bone"
  },
  {
    "id": "42025",
    "pages_id": "15918",
    "seq_id": "29",
    "name": "Temporal Bone"
  },
  {
    "id": "42026",
    "pages_id": "15918",
    "seq_id": "30",
    "name": "Zygomatic Bone"
  },
  {
    "id": "42027",
    "pages_id": "15918",
    "seq_id": "31",
    "name": "Zygomatic Bone"
  },
  {
    "id": "42028",
    "pages_id": "15918",
    "seq_id": "32",
    "name": "Maxilla"
  },
  {
    "id": "42029",
    "pages_id": "15918",
    "seq_id": "33",
    "name": "Maxilla"
  },
  {
    "id": "42030",
    "pages_id": "15918",
    "seq_id": "34",
    "name": "Maxilla"
  }
]