[
  {
    "id": "824",
    "pages_id": "11264",
    "seq_id": "1",
    "name": "Abductor Digiti Minimi Muscle of Foot"
  },
  {
    "id": "825",
    "pages_id": "11264",
    "seq_id": "2",
    "name": "Abductor Digiti Minimi Muscle of Foot"
  },
  {
    "id": "826",
    "pages_id": "11264",
    "seq_id": "3",
    "name": "Abductor Hallucis Muscle"
  },
  {
    "id": "827",
    "pages_id": "11264",
    "seq_id": "4",
    "name": "Abductor Hallucis Muscle"
  },
  {
    "id": "828",
    "pages_id": "11264",
    "seq_id": "5",
    "name": "Adductor Hallucis Muscle"
  },
  {
    "id": "829",
    "pages_id": "11264",
    "seq_id": "6",
    "name": "Adductor Hallucis Muscle"
  },
  {
    "id": "830",
    "pages_id": "11264",
    "seq_id": "7",
    "name": "Adductor Hallucis Muscle"
  },
  {
    "id": "831",
    "pages_id": "11264",
    "seq_id": "8",
    "name": "Adductor Hallucis Muscle"
  },
  {
    "id": "832",
    "pages_id": "11264",
    "seq_id": "9",
    "name": "Adductor Hallucis Muscle"
  },
  {
    "id": "833",
    "pages_id": "11264",
    "seq_id": "10",
    "name": "Adductor Hallucis Muscle"
  },
  {
    "id": "834",
    "pages_id": "11264",
    "seq_id": "11",
    "name": "Adductor Hallucis Muscle"
  },
  {
    "id": "835",
    "pages_id": "11264",
    "seq_id": "12",
    "name": "Adductor Hallucis Muscle"
  },
  {
    "id": "836",
    "pages_id": "11264",
    "seq_id": "13",
    "name": "Adductor Hallucis Muscle"
  },
  {
    "id": "837",
    "pages_id": "11264",
    "seq_id": "14",
    "name": "Adductor Hallucis Muscle"
  },
  {
    "id": "838",
    "pages_id": "11264",
    "seq_id": "15",
    "name": "Adductor Hallucis Muscle"
  },
  {
    "id": "839",
    "pages_id": "11264",
    "seq_id": "16",
    "name": "Adductor Hallucis Muscle"
  },
  {
    "id": "840",
    "pages_id": "11264",
    "seq_id": "17",
    "name": "Adductor Hallucis Muscle"
  },
  {
    "id": "841",
    "pages_id": "11264",
    "seq_id": "18",
    "name": "Adductor Hallucis Muscle"
  },
  {
    "id": "842",
    "pages_id": "11264",
    "seq_id": "19",
    "name": "Anterior Talofibular Ligament"
  },
  {
    "id": "843",
    "pages_id": "11264",
    "seq_id": "20",
    "name": "Calcaneus"
  },
  {
    "id": "844",
    "pages_id": "11264",
    "seq_id": "21",
    "name": "Cuboid Bone"
  },
  {
    "id": "845",
    "pages_id": "11264",
    "seq_id": "22",
    "name": "Cuboid Bone"
  },
  {
    "id": "846",
    "pages_id": "11264",
    "seq_id": "23",
    "name": "Cuboid Bone"
  },
  {
    "id": "847",
    "pages_id": "11264",
    "seq_id": "24",
    "name": "Deep Transverse Metatarsal Ligaments"
  },
  {
    "id": "848",
    "pages_id": "11264",
    "seq_id": "25",
    "name": "Deep Transverse Metatarsal Ligaments"
  },
  {
    "id": "849",
    "pages_id": "11264",
    "seq_id": "26",
    "name": "Deep Transverse Metatarsal Ligaments"
  },
  {
    "id": "850",
    "pages_id": "11264",
    "seq_id": "27",
    "name": "Deep Transverse Metatarsal Ligaments"
  },
  {
    "id": "851",
    "pages_id": "11264",
    "seq_id": "28",
    "name": "Deep Transverse Metatarsal Ligaments"
  },
  {
    "id": "852",
    "pages_id": "11264",
    "seq_id": "29",
    "name": "Deep Transverse Metatarsal Ligaments"
  },
  {
    "id": "853",
    "pages_id": "11264",
    "seq_id": "30",
    "name": "Deep Transverse Metatarsal Ligaments"
  },
  {
    "id": "854",
    "pages_id": "11264",
    "seq_id": "31",
    "name": "Deep Transverse Metatarsal Ligaments"
  },
  {
    "id": "855",
    "pages_id": "11264",
    "seq_id": "32",
    "name": "Distal Phalanges of the Foot"
  },
  {
    "id": "856",
    "pages_id": "11264",
    "seq_id": "33",
    "name": "Distal Phalanges of the Foot"
  },
  {
    "id": "857",
    "pages_id": "11264",
    "seq_id": "34",
    "name": "Distal Phalanges of the Foot"
  },
  {
    "id": "858",
    "pages_id": "11264",
    "seq_id": "35",
    "name": "Distal Phalanges of the Foot"
  },
  {
    "id": "859",
    "pages_id": "11264",
    "seq_id": "36",
    "name": "Distal Phalanges of the Foot"
  },
  {
    "id": "860",
    "pages_id": "11264",
    "seq_id": "37",
    "name": "Fibula"
  },
  {
    "id": "861",
    "pages_id": "11264",
    "seq_id": "38",
    "name": "Fibula"
  },
  {
    "id": "862",
    "pages_id": "11264",
    "seq_id": "39",
    "name": "Fibula"
  },
  {
    "id": "863",
    "pages_id": "11264",
    "seq_id": "40",
    "name": "Flexor Digitorum Longus Tendon"
  },
  {
    "id": "864",
    "pages_id": "11264",
    "seq_id": "41",
    "name": "Flexor Digitorum Longus Tendon"
  },
  {
    "id": "865",
    "pages_id": "11264",
    "seq_id": "42",
    "name": "Flexor Digitorum Longus Tendon"
  },
  {
    "id": "866",
    "pages_id": "11264",
    "seq_id": "43",
    "name": "Flexor Digitorum Longus Tendon"
  },
  {
    "id": "867",
    "pages_id": "11264",
    "seq_id": "44",
    "name": "Flexor Digitorum Longus Tendon"
  },
  {
    "id": "868",
    "pages_id": "11264",
    "seq_id": "45",
    "name": "Flexor Digiti Minimi Brevis Muscle of Foot"
  },
  {
    "id": "869",
    "pages_id": "11264",
    "seq_id": "46",
    "name": "Flexor Digiti Minimi Brevis Muscle of Foot"
  },
  {
    "id": "870",
    "pages_id": "11264",
    "seq_id": "47",
    "name": "Flexor Digitorum Longus Muscle"
  },
  {
    "id": "871",
    "pages_id": "11264",
    "seq_id": "48",
    "name": "Flexor Hallucis Brevis Muscle"
  },
  {
    "id": "872",
    "pages_id": "11264",
    "seq_id": "49",
    "name": "Flexor Hallucis Brevis Muscle"
  },
  {
    "id": "873",
    "pages_id": "11264",
    "seq_id": "50",
    "name": "Flexor Hallucis Brevis Muscle"
  },
  {
    "id": "874",
    "pages_id": "11264",
    "seq_id": "51",
    "name": "Flexor Hallucis Longus Muscle"
  },
  {
    "id": "875",
    "pages_id": "11264",
    "seq_id": "52",
    "name": "Flexor Hallucis Longus Tendon"
  },
  {
    "id": "876",
    "pages_id": "11264",
    "seq_id": "53",
    "name": "Flexor Hallucis Longus Tendon"
  },
  {
    "id": "877",
    "pages_id": "11264",
    "seq_id": "54",
    "name": "Flexor Hallucis Longus Tendon"
  },
  {
    "id": "878",
    "pages_id": "11264",
    "seq_id": "55",
    "name": "Flexor Hallucis Longus Tendon"
  },
  {
    "id": "879",
    "pages_id": "11264",
    "seq_id": "56",
    "name": "Flexor Hallucis Longus Tendon"
  },
  {
    "id": "880",
    "pages_id": "11264",
    "seq_id": "57",
    "name": "Flexor Retinaculum of Foot"
  },
  {
    "id": "881",
    "pages_id": "11264",
    "seq_id": "58",
    "name": "Inferior Extensor Retinaculum"
  },
  {
    "id": "882",
    "pages_id": "11264",
    "seq_id": "59",
    "name": "Inferior Extensor Retinaculum"
  },
  {
    "id": "883",
    "pages_id": "11264",
    "seq_id": "60",
    "name": "Interosseous Membrane of the Leg"
  },
  {
    "id": "884",
    "pages_id": "11264",
    "seq_id": "61",
    "name": "Long Plantar Ligament"
  },
  {
    "id": "885",
    "pages_id": "11264",
    "seq_id": "62",
    "name": "Long Plantar Ligament"
  },
  {
    "id": "886",
    "pages_id": "11264",
    "seq_id": "63",
    "name": "Lumbrical Muscles of Foot"
  },
  {
    "id": "887",
    "pages_id": "11264",
    "seq_id": "64",
    "name": "Lumbrical Muscles of Foot"
  },
  {
    "id": "888",
    "pages_id": "11264",
    "seq_id": "65",
    "name": "Lumbrical Muscles of Foot"
  },
  {
    "id": "889",
    "pages_id": "11264",
    "seq_id": "66",
    "name": "Lumbrical Muscles of Foot"
  },
  {
    "id": "890",
    "pages_id": "11264",
    "seq_id": "67",
    "name": "Medial Cuneiform Bone"
  },
  {
    "id": "891",
    "pages_id": "11264",
    "seq_id": "68",
    "name": "Middle Phalanges of the Foot"
  },
  {
    "id": "892",
    "pages_id": "11264",
    "seq_id": "69",
    "name": "Middle Phalanges of the Foot"
  },
  {
    "id": "893",
    "pages_id": "11264",
    "seq_id": "70",
    "name": "Middle Phalanges of the Foot"
  },
  {
    "id": "894",
    "pages_id": "11264",
    "seq_id": "71",
    "name": "Middle Phalanges of the Foot"
  },
  {
    "id": "895",
    "pages_id": "11264",
    "seq_id": "72",
    "name": "Middle Phalanges of the Foot"
  },
  {
    "id": "896",
    "pages_id": "11264",
    "seq_id": "73",
    "name": "Middle Phalanges of the Foot"
  },
  {
    "id": "897",
    "pages_id": "11264",
    "seq_id": "74",
    "name": "Middle Phalanges of the Foot"
  },
  {
    "id": "898",
    "pages_id": "11264",
    "seq_id": "75",
    "name": "Middle Phalanges of the Foot"
  },
  {
    "id": "899",
    "pages_id": "11264",
    "seq_id": "76",
    "name": "Metatarsal Bones"
  },
  {
    "id": "900",
    "pages_id": "11264",
    "seq_id": "77",
    "name": "Metatarsal Bones"
  },
  {
    "id": "901",
    "pages_id": "11264",
    "seq_id": "78",
    "name": "Metatarsal Bones"
  },
  {
    "id": "902",
    "pages_id": "11264",
    "seq_id": "79",
    "name": "Metatarsal Bones"
  },
  {
    "id": "903",
    "pages_id": "11264",
    "seq_id": "80",
    "name": "Metatarsal Bones"
  },
  {
    "id": "904",
    "pages_id": "11264",
    "seq_id": "81",
    "name": "Metatarsal Bones"
  },
  {
    "id": "905",
    "pages_id": "11264",
    "seq_id": "82",
    "name": "Metatarsal Bones"
  },
  {
    "id": "906",
    "pages_id": "11264",
    "seq_id": "83",
    "name": "Metatarsal Bones"
  },
  {
    "id": "907",
    "pages_id": "11264",
    "seq_id": "84",
    "name": "Metatarsal Bones"
  },
  {
    "id": "908",
    "pages_id": "11264",
    "seq_id": "85",
    "name": "Metatarsal Bones"
  },
  {
    "id": "909",
    "pages_id": "11264",
    "seq_id": "86",
    "name": "Metatarsal Bones"
  },
  {
    "id": "910",
    "pages_id": "11264",
    "seq_id": "87",
    "name": "Metatarsal Bones"
  },
  {
    "id": "911",
    "pages_id": "11264",
    "seq_id": "88",
    "name": "Metatarsal Bones"
  },
  {
    "id": "912",
    "pages_id": "11264",
    "seq_id": "89",
    "name": "Metatarsal Bones"
  },
  {
    "id": "913",
    "pages_id": "11264",
    "seq_id": "90",
    "name": "Talus"
  },
  {
    "id": "914",
    "pages_id": "11264",
    "seq_id": "91",
    "name": "Talus"
  },
  {
    "id": "915",
    "pages_id": "11264",
    "seq_id": "92",
    "name": "Talus"
  },
  {
    "id": "916",
    "pages_id": "11264",
    "seq_id": "93",
    "name": "Talus"
  },
  {
    "id": "917",
    "pages_id": "11264",
    "seq_id": "94",
    "name": "Tibia"
  },
  {
    "id": "918",
    "pages_id": "11264",
    "seq_id": "95",
    "name": "Tibia"
  },
  {
    "id": "919",
    "pages_id": "11264",
    "seq_id": "96",
    "name": "Tibia"
  },
  {
    "id": "920",
    "pages_id": "11264",
    "seq_id": "97",
    "name": "Tibia"
  },
  {
    "id": "921",
    "pages_id": "11264",
    "seq_id": "98",
    "name": "Tibia"
  },
  {
    "id": "922",
    "pages_id": "11264",
    "seq_id": "99",
    "name": "Tibia"
  },
  {
    "id": "923",
    "pages_id": "11264",
    "seq_id": "100",
    "name": "Tibialis Posterior Tendon"
  },
  {
    "id": "924",
    "pages_id": "11264",
    "seq_id": "101",
    "name": "Tibialis Posterior Tendon"
  },
  {
    "id": "925",
    "pages_id": "11264",
    "seq_id": "102",
    "name": "Tibialis Posterior Tendon"
  },
  {
    "id": "926",
    "pages_id": "11264",
    "seq_id": "103",
    "name": "Quadratus Plantae Muscle"
  },
  {
    "id": "927",
    "pages_id": "11264",
    "seq_id": "104",
    "name": "Plantaris Tendon"
  },
  {
    "id": "928",
    "pages_id": "11264",
    "seq_id": "105",
    "name": "Peroneus Brevis Muscle"
  }
]